Workbook

Sheet Balanço Contab
A1: Entidade: | B1: JJ TEIXEIRA, SA
B2: Wood Engineeing Tailor
B4: Balanço individual a 31 de dezembro | F4: (em euros)
B5: Rubricas | C5: Notas | D5: Anos
D6: 2022 | E6: 2023 | F6: 2024
B7: ATIVO
B8: Ativo não corrente
B9: Ativos fixos tangíveis | C9: 5 | D9: 19459800 | E9: 18666572 | F9: 20729866
B10: Propriedades de investimento | C10: 6 | D10: 78216 | E10: 76393 | F10: 74571
B11: Ativos intangíveis | C11: 7 | D11: 278210 | E11: 261041 | F11: 242369
B12: Participações financeiras - Outros métodos | C12: 8 | D12: 160000 | E12: 166000 | F12: 166000
B13: Outros ativos financeiros | D13: 2392 | E13: 2944 | F13: 2887
B14: Ativos por impostos diferidos | C14: 9 | D14: 3543112 | E14: 2870650 | F14: 3308871
D15: =SUM(D9:D14) -> 23521730 | E15: =SUM(E9:E14) -> 22043600 | F15: =SUM(F9:F14) -> 24524564
B16: Ativo corrente
B17: Inventários | C17: 10 | D17: 2476629 | E17: 2368546 | F17: 2667287
B18: Clientes | C18: 11 | D18: 10993343 | E18: 13433628 | F18: 15033498
B19: Estado e Outros Entes Públicos | C19: 12 | D19: 299077 | E19: 254510 | F19: 764059
B20: Outros créditos a receber | C20: 13 | D20: 4152529 | E20: 5511417 | F20: 7076559
B21: Diferimentos | C21: 14 | D21: 175917 | E21: 187514 | F21: 206335 | G21: Diferimentos: são Gastos a reconhecer (nota 14)
B22: Caixa e depósitos bancários | C22: 4 | D22: 2257927 | E22: 4138413 | F22: 1799870
D23: =SUM(D17:D22) -> 20355422 | E23: =SUM(E17:E22) -> 25894028 | F23: =SUM(F17:F22) -> 27547608
B24: Total do Ativo | D24: =D15+D23 -> 43877152 | E24: =E15+E23 -> 47937627 | F24: =F15+F23 -> 52072172
B25: CAPITAL PRÓPRIO PASSIVO
B26: Capital Próprio
B27: Capital realizado | C27: 15 | D27: 11740455 | E27: 11740455 | F27: 11740455
B28: Prémios de emissão | C28: 17 | D28: 959545 | E28: 959545 | F28: 959545
B29: Reservas Legais | C29: 18 | D29: 658278 | E29: 773685 | F29: 891080
B30: Outras reservas | C30: 16 | D30: 4710221 | E30: 4710221 | F30: 4710221
B31: Resultados Transitados | C31: 19 | D31: -2266539 | E31: -73815 | F31: 2156686
B32: Outras variações no capital próprio | C32: 20 | D32: 2482464 | E32: 1982771 | F32: 1622563
B33: Resultado liquido do período | D33: 2308131 | E33: 2347896 | F33: 2279250
B34: Total do Capital Próprio | D34: =SUM(D27:D33) -> 20592555 | E34: =SUM(E27:E33) -> 22440758 | F34: =SUM(F27:F33) -> 24359800
B36: Passivo
B37: Passivo não corrente
B38: Provisões | D38: 0 | E38: 0 | F38: 0
B39: Financiamentos obtidos | C39: 23 | D39: 10408410 | E39: 9500813 | F39: 13988727
B40: Outras dívidas a pagar | C40: 24 | D40: 3974890 | E40: 3334245 | F40: 1761814
D41: =SUM(D38:D40) -> 14383300 | E41: =SUM(E38:E40) -> 12835058 | F41: =SUM(F38:F40) -> 15750541
B42: Passivo Corrente
B43: Fornecedores | C43: 21 | D43: 1415895 | E43: 633029 | F43: 721181
B44: Adiantamentos de clientes | C44: 22 | D44: 174400 | E44: 1889441 | F44: 1863058
B45: Estado e Outros Entes Públicos | C45: 12 | D45: 425515 | E45: 408241 | F45: 400871
B46: Financiamentos Obtidos | C46: 23 | D46: 6052620 | E46: 8118404 | F46: 7106798
B47: Outras dívidas a pagar | C47: 24 | D47: 739384 | E47: 1304192 | F47: 1772055
B48: Diferimentos | C48: 14 | D48: 93483 | E48: 308504 | F48: 97868 | G48: Diferimentos: são Rendimentos a reconhecer (nota 14)
D49: =SUM(D43:D48) -> 8901297 | E49: =SUM(E43:E48) -> 12661811 | F49: =SUM(F43:F48) -> 11961831
B50: Total do Passivo | D50: =D49+D41 -> 23284597 | E50: =E49+E41 -> 25496869 | F50: =F49+F41 -> 27712372
B51: Total do Capital Próprio e do Passivo | D51: =D34+D50 -> 43877152 | E51: =E34+E50 -> 47937627 | F51: =F34+F50 -> 52072172
D53: =D51-D24 -> 0 | E53: =E51-E24 -> 0 | F53: =F51-F24 -> 0
B55: NOTAS DO ANEXO AO BALANÇO
B57: 12 - ESTADO E OUTROS ENTES PUBLICOS CORRENTES ATIVOS | H57: 12 - ESTADO E OUTROS ENTES PUBLICOS CORRENTES PASSIVOS
B58: No final do exercício, a rúbrica de "Estado e Outros Entes Públicos Ativo" apresentava a seguinte composição: | H58: No final do exercício, a rúbrica de "Estado e Outros Entes Públicos Passivo" apresentava a seguinte composição:
C59: Notas | D59: 2022 | E59: 2023 | F59: 2024 | I59: Notas | J59: 2022 | K59: 2023 | L59: 2024
B60: IRC | F60: 182949 | H60: IRC | J60: 36916 | K60: 31714 | L60: 94223 | M60: TP
B61: IRS | H61: IRS | J61: 91627 | K61: 95528 | M61: RC
B62: IVA (reembolsos) | D62: 299077 | E62: 254510 | F62: 581110 | H62: IVA | M62: RC
B63: Segurança Social | H63: Segurança Social | J63: 296729 | K63: 280999 | L63: 306648 | M63: RC
B64: Outros | H64: Outros | J64: 243 | M64: RC | N64: Pressuposto de que estes saldos derivam de operações do ãmbito da atividade de exploração da empresa
B65: (saldo da conta EOEP inclui IRC (TA) e IVA (NC), pressuposto de que este saldo resultou de operações do àmbito da atividade de exploração)
J66: =SUM(J60:J64)-D45 -> 0 | K66: =SUM(K60:K64)-E45 -> 0 | L66: =SUM(L60:L64)-F45 -> 0
B68: 13 - OUTROS CRÉDITOS A RECEBER
B69: No final do exercício, a rúbrica de "Outros créditos a receber" apresentava a seguinte composição:
C70: Notas | D70: 2022 | E70: 2023 | F70: 2024
B71: Adiantamentos a fornecedores | D71: 159197 | E71: 154858 | F71: 387998
B72: Adiantamentos ao pessoal | D72: 19164 | E72: 35792 | F72: 200326 | G72: NC
B73: Obras plurianuais | D73: 3717384 | E73: 4874137 | F73: 5876449
B74: Subsídios | D74: 4242 | E74: 23462 | F74: 0
B75: Cauções | D75: 13181 | E75: 13181 | F75: 13181 | G75: TA | H75: (relacionados com processos judiciais)
B76: Outros devedores | D76: 239361 | E76: 409987 | F76: 598605 | G76: NC | H76: (pressuposto de que este saldo resultou de operações do âmbito da atividade de ecploração
D78: =SUM(D71:D76)-D20 -> 0 | E78: =SUM(E71:E76)-E20 -> 0 | F78: =SUM(F71:F76)-F20 -> 0
B80: 14 - DIFERIMENTOS
B81: No final do exercício, a rúbrica "Diferimentos - Ativos" apresentava a seguinte composição: | H81: No final do exercício, a rúbrica "Diferimentos - Passivos" apresentava a seguinte composição:
C82: Notas | D82: 2022 | E82: 2023 | F82: 2024 | I82: Notas | J82: 2022 | K82: 2023 | L82: 2024
B83: Seguros | C83: 14 | D83: 47070 | E83: 32435 | F83: 45137 | H83: Rendimentos a reconhecer | I83: 14 | J83: 93483 | K83: 308504 | L83: 97868
B84: Outros | C84: 14 | D84: 128847 | E84: 155079 | F84: 161198
D86: =SUM(D83:D84)-D21 -> 0 | E86: =SUM(E83:E84)-E21 -> 0 | F86: =SUM(F83:F84)-F21 -> 0
B88: 24 - OUTRAS DÍVIDAS A PAGAR
B89: No final do exercício, a rúbrica de "Outras dívidas a pagar não correntes" apresentava a seguinte composição:
C90: Notas | D90: 2022 | E90: 2023 | F90: 2024
B91: Cred. acréscimos de gastos subs. pessoal | C91: 24 | D91: 1010567 | E91: 400 | F91: 400
B92: Cred. acréscimos de gastos - diversos | C92: 24 | D92: 284261 | E92: 595113 | F92: 485290
B93: Outros credores diversos | C93: 24 | D93: 31329
B94: Total (1) | D94: =SUM(D91:D93) -> 1326157 | E94: =SUM(E91:E93) -> 595513 | F94: =SUM(F91:F93) -> 485690
B96: No final do exercício, a rúbrica de "Outras dívidas a pagar não correntes - Acionistas/Sócios" apresentava a seguinte composição:
C97: Notas | D97: 2022 | E97: 2023 | F97: 2024
B98: Maria Jacinta Rocha Sousa | C98: 24 | D98: 174063 | E98: 174063 | F98: 174063
B99: João Evangelista Nunes | C99: 24 | D99: 22500 | E99: 22500 | F99: 23000
B100: Fundo Revitalizar Norte | C100: 24 | D100: 1800000 | E100: 1800000 | F100: 737850
B101: Juros | C101: 24 | D101: 652170 | E101: 742169 | F101: 341211
B102: Total (2) | D102: =SUM(D98:D101) -> 2648733 | E102: =SUM(E98:E101) -> 2738732 | F102: =SUM(F98:F101) -> 1276124
B104: Total (1) + Total (2) | D104: =D94+D102 -> 3974890 | E104: =E94+E102 -> 3334245 | F104: =F94+F102 -> 1761814 | G104: É o valor das Outras dívidas a pagar do Passivo não corrente do Balanço
D105: =D104-D40 -> 0 | E105: =E104-E40 -> 0 | F105: =F104-F40 -> 0 | G105: A nota 24 apenas apresenta o detalhe das dívidas do Passivo não corrente.
G106: Logo, quanto às dívidas do Passivo corrente, não há informação detalhada. Pelo que se pressupõe tratar-se de dívidas decorrentes da atividade de exploração da empresa.

Sheet Balanço Funcional
A2: Entidade: | B2: JJ Teixeira, S.A.
B4: Balanço Funcional | G4: (em euros)
B5: Rubricas | C5: Notas | E5: Anos
D6: 2021 | E6: 2022 | F6: 2023 | G6: 2024
B7: Aplicações Fixas Líquidas
B8: ='Balanço Contab'!B9 -> Ativos fixos tangíveis | C8: ='Balanço Contab'!C9 -> 5 | D8: 21318266 | E8: ='Balanço Contab'!D9 -> 19459800 | F8: ='Balanço Contab'!E9 -> 18666572 | G8: ='Balanço Contab'!F9 -> 20729866
B9: ='Balanço Contab'!B10 -> Propriedades de investimento | C9: ='Balanço Contab'!C10 -> 6 | D9: 80038 | E9: ='Balanço Contab'!D10 -> 78216 | F9: ='Balanço Contab'!E10 -> 76393 | G9: ='Balanço Contab'!F10 -> 74571
B10: ='Balanço Contab'!B11 -> Ativos intangíveis | C10: ='Balanço Contab'!C11 -> 7 | D10: 312295 | E10: ='Balanço Contab'!D11 -> 278210 | F10: ='Balanço Contab'!E11 -> 261041 | G10: ='Balanço Contab'!F11 -> 242369
B11: ='Balanço Contab'!B12 -> Participações financeiras - Outros métodos | C11: ='Balanço Contab'!C12 -> 8 | D11: 160000 | E11: ='Balanço Contab'!D12 -> 160000 | F11: ='Balanço Contab'!E12 -> 166000 | G11: ='Balanço Contab'!F12 -> 166000
B12: ='Balanço Contab'!B13 -> Outros ativos financeiros | D12: 345 | E12: ='Balanço Contab'!D13 -> 2392 | F12: ='Balanço Contab'!E13 -> 2944 | G12: ='Balanço Contab'!F13 -> 2887
B13: ='Balanço Contab'!B14 -> Ativos por impostos diferidos | C13: ='Balanço Contab'!C14 -> 9 | D13: 3480361 | E13: ='Balanço Contab'!D14 -> 3543112 | F13: ='Balanço Contab'!E14 -> 2870650 | G13: ='Balanço Contab'!F14 -> 3308871
B14: Outros créditos a receber | C14: 13 | D14: 13181 | E14: ='Balanço Contab'!D75 -> 13181 | F14: ='Balanço Contab'!E75 -> 13181 | G14: ='Balanço Contab'!F75 -> 13181 | H14: Cauções (extra exploração; valor constante no triénio)
D15: =SUM(D8:D14) -> 25364486 | E15: =SUM(E8:E14) -> 23534911 | F15: =SUM(F8:F14) -> 22056780 | G15: =SUM(G8:G14) -> 24537744
B16: Necessidades Cíclicas | H16: Ver se a Ativos não correntes detidos para venda entram
B17: ='Balanço Contab'!B17 -> Inventários | C17: ='Balanço Contab'!C17 -> 10 | D17: 2142568 | E17: ='Balanço Contab'!D17 -> 2476629 | F17: ='Balanço Contab'!E17 -> 2368546 | G17: ='Balanço Contab'!F17 -> 2667287
B18: ='Balanço Contab'!B18 -> Clientes | C18: ='Balanço Contab'!C18 -> 11 | D18: 9505101 | E18: ='Balanço Contab'!D18 -> 10993343 | F18: ='Balanço Contab'!E18 -> 13433628 | G18: ='Balanço Contab'!F18 -> 15033498
B19: ='Balanço Contab'!B19 -> Estado e Outros Entes Públicos | C19: ='Balanço Contab'!C19 -> 12 | D19: 247309 | E19: ='Balanço Contab'!D62 -> 299077 | F19: ='Balanço Contab'!E62 -> 254510 | G19: ='Balanço Contab'!F62 -> 581110 | H19: IVA
B20: ='Balanço Contab'!B20 -> Outros créditos a receber | C20: ='Balanço Contab'!C20 -> 13 | D20: =219243+50602+2678539+668447 -> 3616831 | E20: ='Balanço Contab'!D71+'Balanço Contab'!D72+'Balanço Contab'!D73+'Balanço Contab'!D76 -> 4135106 | F20: ='Balanço Contab'!E71+'Balanço Contab'!E72+'Balanço Contab'!E73+'Balanço Contab'!E76 -> 5474774 | G20: ='Balanço Contab'!F71+'Balanço Contab'!F72+'Balanço Contab'!F73+'Balanço Contab'!F76 -> 7063378 | H20: Adiant. fornec.; Adiant. pessoal; Obras plurianuais; Outros
B21: ='Balanço Contab'!B21 -> Diferimentos | C21: ='Balanço Contab'!C21 -> 14 | D21: 135936 | E21: ='Balanço Contab'!D83+'Balanço Contab'!D84 -> 175917 | F21: ='Balanço Contab'!E83+'Balanço Contab'!E84 -> 187514 | G21: ='Balanço Contab'!F83+'Balanço Contab'!F84 -> 206335 | H21: Seguros; Outros
D22: =SUM(D17:D21) -> 15647745 | E22: =SUM(E17:E21) -> 18080072 | F22: =SUM(F17:F21) -> 21718972 | G22: =SUM(G17:G21) -> 25551608
B23: Tesouraria Ativa
B24: Estado e Outros Entes Públicos (IRC) | C24: 12 | D24: 31 | E24: ='Balanço Contab'!D60 -> 0 | F24: ='Balanço Contab'!E60 -> 0 | G24: ='Balanço Contab'!F60 -> 182949
B25: Outros créditos a receber | C25: 13 | D25: 11313 | E25: ='Balanço Contab'!D74 -> 4242 | F25: ='Balanço Contab'!E74 -> 23462 | G25: ='Balanço Contab'!F74 -> 0 | H25: Subsídios
B26: ='Balanço Contab'!B22 -> Caixa e depósitos bancários | C26: 4 | D26: 1461954 | E26: ='Balanço Contab'!D22 -> 2257927 | F26: ='Balanço Contab'!E22 -> 4138413 | G26: ='Balanço Contab'!F22 -> 1799870
D27: =SUM(D24:D26) -> 1473298 | E27: =SUM(E24:E26) -> 2262169 | F27: =SUM(F24:F26) -> 4161875 | G27: =SUM(G24:G26) -> 1982819
B28: ='Balanço Contab'!B24 -> Total do Ativo | D28: =D15+D22+D27 -> 42485529 | E28: =E15+E22+E27 -> 43877152 | F28: =F15+F22+F27 -> 47937627 | G28: =G15+G22+G27 -> 52072172 | I28: =E28-'Balanço Contab'!D24 -> 0 | J28: =F28-'Balanço Contab'!E24 -> 0 | K28: =G28-'Balanço Contab'!F24 -> 0
B29: Recursos Estáveis
B30: ='Balanço Contab'!B26 -> Capital Próprio
B31: ='Balanço Contab'!B27 -> Capital realizado | C31: ='Balanço Contab'!C27 -> 15 | D31: 11740455 | E31: ='Balanço Contab'!D27 -> 11740455 | F31: ='Balanço Contab'!E27 -> 11740455 | G31: ='Balanço Contab'!F27 -> 11740455
B32: ='Balanço Contab'!B28 -> Prémios de emissão | C32: ='Balanço Contab'!C28 -> 17 | D32: 959545 | E32: ='Balanço Contab'!D28 -> 959545 | F32: ='Balanço Contab'!E28 -> 959545 | G32: ='Balanço Contab'!F28 -> 959545
B33: ='Balanço Contab'!B29 -> Reservas Legais | C33: ='Balanço Contab'!C29 -> 18 | D33: 658278 | E33: ='Balanço Contab'!D29 -> 658278 | F33: ='Balanço Contab'!E29 -> 773685 | G33: ='Balanço Contab'!F29 -> 891080
B34: ='Balanço Contab'!B30 -> Outras reservas | C34: ='Balanço Contab'!C30 -> 16 | D34: 4710221 | E34: ='Balanço Contab'!D30 -> 4710221 | F34: ='Balanço Contab'!E30 -> 4710221 | G34: ='Balanço Contab'!F30 -> 4710221
B35: ='Balanço Contab'!B31 -> Resultados Transitados | C35: ='Balanço Contab'!C31 -> 19 | D35: -1804293 | E35: ='Balanço Contab'!D31 -> -2266539 | F35: ='Balanço Contab'!E31 -> -73815 | G35: ='Balanço Contab'!F31 -> 2156686
B36: ='Balanço Contab'!B32 -> Outras variações no capital próprio | C36: ='Balanço Contab'!C32 -> 20 | D36: 3144447 | E36: ='Balanço Contab'!D32 -> 2482464 | F36: ='Balanço Contab'!E32 -> 1982771 | G36: ='Balanço Contab'!F32 -> 1622563
B37: ='Balanço Contab'!B33 -> Resultado liquido do período | D37: -462246 | E37: ='Balanço Contab'!D33 -> 2308131 | F37: ='Balanço Contab'!E33 -> 2347896 | G37: ='Balanço Contab'!F33 -> 2279250
B38: ='Balanço Contab'!B34 -> Total do Capital Próprio | D38: =SUM(D31:D37) -> 18946407 | E38: =SUM(E31:E37) -> 20592555 | F38: =SUM(F31:F37) -> 22440758 | G38: =SUM(G31:G37) -> 24359800
B40: ='Balanço Contab'!B37 -> Passivo não corrente
B41: ='Balanço Contab'!B38 -> Provisões | D41: 0 | E41: ='Balanço Contab'!D38 -> 0 | F41: ='Balanço Contab'!E38 -> 0 | G41: ='Balanço Contab'!F38 -> 0
B42: ='Balanço Contab'!B39 -> Financiamentos obtidos | C42: ='Balanço Contab'!C39 -> 23 | D42: 10522437 | E42: ='Balanço Contab'!D39 -> 10408410 | F42: ='Balanço Contab'!E39 -> 9500813 | G42: ='Balanço Contab'!F39 -> 13988727
B43: ='Balanço Contab'!B40 -> Outras dívidas a pagar | C43: ='Balanço Contab'!C40 -> 24 | D43: 4032293 | E43: ='Balanço Contab'!D40 -> 3974890 | F43: ='Balanço Contab'!E40 -> 3334245 | G43: ='Balanço Contab'!F40 -> 1761814
D44: =+D42+D43 -> 14554730 | E44: =SUM(E41:E43) -> 14383300 | F44: =SUM(F41:F43) -> 12835058 | G44: =SUM(G41:G43) -> 15750541
D45: =SUM(D38+D44) -> 33501137 | E45: =E38+E44 -> 34975855 | F45: =F38+F44 -> 35275816 | G45: =G38+G44 -> 40110341
B46: Recursos Cíclicos
B47: ='Balanço Contab'!B43 -> Fornecedores | C47: ='Balanço Contab'!C43 -> 21 | D47: 710998 | E47: ='Balanço Contab'!D43 -> 1415895 | F47: ='Balanço Contab'!E43 -> 633029 | G47: ='Balanço Contab'!F43 -> 721181
B48: ='Balanço Contab'!B44 -> Adiantamentos de clientes | C48: ='Balanço Contab'!C44 -> 22 | D48: 288801 | E48: ='Balanço Contab'!D44 -> 174400 | F48: ='Balanço Contab'!E44 -> 1889441 | G48: ='Balanço Contab'!F44 -> 1863058
B49: ='Balanço Contab'!B45 -> Estado e Outros Entes Públicos | C49: ='Balanço Contab'!C45 -> 12 | D49: =0+375385+205 -> 375590 | E49: ='Balanço Contab'!J61+'Balanço Contab'!J62+'Balanço Contab'!J63+'Balanço Contab'!J64 -> 388599 | F49: ='Balanço Contab'!K61+'Balanço Contab'!K62+'Balanço Contab'!K63+'Balanço Contab'!K64 -> 376527 | G49: ='Balanço Contab'!L61+'Balanço Contab'!L62+'Balanço Contab'!L63+'Balanço Contab'!L64 -> 306648 | H49: IRS; Seg. Social; Outros
B50: ='Balanço Contab'!B47 -> Outras dívidas a pagar | C50: ='Balanço Contab'!C47 -> 24 | D50: 914970 | E50: ='Balanço Contab'!D47 -> 739384 | F50: ='Balanço Contab'!E47 -> 1304192 | G50: ='Balanço Contab'!F47 -> 1772055 | H50: Pressuposto de exploração
B51: ='Balanço Contab'!B48 -> Diferimentos | C51: ='Balanço Contab'!C48 -> 14 | D51: 33500 | E51: ='Balanço Contab'!J83 -> 93483 | F51: ='Balanço Contab'!K83 -> 308504 | G51: ='Balanço Contab'!L83 -> 97868 | H51: Rendimentos a reconhecer
D52: =SUM(D47:D51) -> 2323859 | E52: =SUM(E47:E51) -> 2811761 | F52: =SUM(F47:F51) -> 4511693 | G52: =SUM(G47:G51) -> 4760810
B53: Tesouraria Passiva
B54: ='Balanço Contab'!B46 -> Financiamentos Obtidos | C54: ='Balanço Contab'!C46 -> 23 | D54: 6640967 | E54: ='Balanço Contab'!D46 -> 6052620 | F54: ='Balanço Contab'!E46 -> 8118404 | G54: ='Balanço Contab'!F46 -> 7106798
B55: Estado e Outros Entes Públicos (IRC) | C55: 12 | D55: 94549 | E55: ='Balanço Contab'!J60 -> 36916 | F55: ='Balanço Contab'!K60 -> 31714 | G55: ='Balanço Contab'!L60 -> 94223
D56: =SUM(D54:D55) -> 6735516 | E56: =SUM(E54:E55) -> 6089536 | F56: =SUM(F54:F55) -> 8150118 | G56: =SUM(G54:G55) -> 7201021
B57: ='Balanço Contab'!B50 -> Total do Passivo | D57: =SUM(D44+D52+D56) -> 23614105 | E57: =E44+E52+E56 -> 23284597 | F57: =F44+F52+F56 -> 25496869 | G57: =G44+G52+G56 -> 27712372
B58: ='Balanço Contab'!B51 -> Total do Capital Próprio e do Passivo | D58: =D38+D57 -> 42560512 | E58: =E57+E38 -> 43877152 | F58: =F57+F38 -> 47937627 | G58: =G57+G38 -> 52072172 | I58: =E58-'Balanço Contab'!D51 -> 0 | J58: =F58-'Balanço Contab'!E51 -> 0 | K58: =G58-'Balanço Contab'!F51 -> 0
E60: =E58-E28 -> 0 | F60: =F58-F28 -> 0 | G60: =G58-G28 -> 0
B62: Quadro E.1: Indicadores FMF, NFM e TL | G62: (em euros)
B63: Rubricas e Indicadores | C63: Notas | E63: Anos
E64: 2022 | F64: 2023 | G64: 2024
B65: Recursos Estáveis | E65: =+E45 -> 34975855 | F65: =+F45 -> 35275816 | G65: =+G45 -> 40110341
B66: Aplicações Fixas Líquidas | E66: =+E15 -> 23534911 | F66: =+F15 -> 22056780 | G66: =+G15 -> 24537744
B67: FMF = RE - AFL | E67: =E65-E66 -> 11440944 | F67: =F65-F66 -> 13219036 | G67: =G65-G66 -> 15572596
B68: Necessidades Cíclicas | E68: =+E22 -> 18080072 | F68: =+F22 -> 21718972 | G68: =+G22 -> 25551608
B69: Recursos Cíclicos | E69: =+E52 -> 2811761 | F69: =+F52 -> 4511693 | G69: =+G52 -> 4760810
B70: NFM = NC - RC | E70: =E68-E69 -> 15268311 | F70: =F68-F69 -> 17207278 | G70: =G68-G69 -> 20790798
B71: Tesouraria Ativa | E71: =+E27 -> 2262169 | F71: =+F27 -> 4161875 | G71: =+G27 -> 1982819
B72: Tesouraria Passiva | E72: =+E56 -> 6089536 | F72: =+F56 -> 8150118 | G72: =+G56 -> 7201021
B73: TL = TA - TP | E73: =E71-E72 -> -3827367 | F73: =F71-F72 -> -3988243 | G73: =G71-G72 -> -5218202
B74: TL = FMF - NFM | E74: =E67-E70 -> -3827367 | F74: =F67-F70 -> -3988243 | G74: =G67-G70 -> -5218202

Sheet DR Contab
A2: Entidade: | B2: JJ Teixeira, S.A.
B4: Demonstração dos resultados a 31 de dezembro | F4: (em euros)
B5: RENDIMENTOS E GASTOS | C5: Notas | D5: Anos
D6: 2022 | E6: 2023 | F6: 2024
B7: Vendas e serviços prestados | C7: 25 | D7: 34414527 | E7: 36103943 | F7: 39540477 | G7: =((F7-E7)/E7)*100 -> 9.5184451
B8: Subsídios à exploração | C8: 26 | D8: 71600 | E8: 42589 | F8: 870
B9: Variação nos inventários da produção | C9: 27 | D9: 3248 | E9: -59213 | F9: 131969
B10: Trabalhos para a própria entidade
B11: Custo das mercadorias vendidas e matérias consumidas | C11: 28 | D11: -9270182 | E11: -9474096 | F11: -10429861
B12: Fornecimentos e serviços externos | C12: 29 | D12: -10472728 | E12: -10062717 | F12: -13103785
B13: Gastos com pessoal | C13: 30 | D13: -8709967 | E13: -9570544 | F13: -10311572
B14: Imparidade de inventários (perdas/reversões) | C14: 10 | D14: 24000 | E14: -7482 | F14: 7482
B15: Imparidade de dívidas a receber (perdas/reversões) | C15: 11 | D15: -1074082 | E15: -530467 | F15: -403235
B16: Aumentos/reduções de justo valor | D16: -211 | E16: 91 | F16: -58
B17: Ganhos/Perdas em empresas do grupo
B18: Outros rendimentos e ganhos | C18: 31 | D18: 1262832 | E18: 768393 | F18: 677442
B19: Outros gastos e perdas | C19: 32 | D19: -230470 | E19: -285783 | F19: -346147
B20: Resultado antes de depreciações, gastos de financiamento e impostos | D20: =SUM(D7:D19) -> 6018567 | E20: =SUM(E7:E19) -> 6924714 | F20: =SUM(F7:F19) -> 5763582
B21: Gastos/reversões de depreciação e de amortização | C21: 33 | D21: -3102483 | E21: -2957566 | F21: -2761538
B22: Imparidade de investimentos depreciáveis/amortizáveis (perdas/reversões)
B23: Resultado Operacional (antes de gastos de financiamento e impostos) | D23: =SUM(D20:D22) -> 2916084 | E23: =SUM(E20:E22) -> 3967148 | F23: =SUM(F20:F22) -> 3002044
B24: Juros e rendimentos similares obtidos | C24: 34 | D24: 1595 | E24: 93572 | F24: 47799
B25: Juros de empresas do grupo
B26: Juros e gastos similares suportados | C26: 35 | D26: -635383 | E26: -972006 | F26: -1151303
B27: Resultado antes de impostos | D27: =SUM(D23:D26) -> 2282296 | E27: =SUM(E23:E26) -> 3088714 | F27: =SUM(F23:F26) -> 1898540
B28: Imposto s/ rendimento do período | D28: 25835 | E28: -740818 | F28: 380710
B29: Imposto diferido
B30: Resultado liquido do período | D30: =SUM(D27:D29) -> 2308131 | E30: =SUM(E27:E29) -> 2347896 | F30: =SUM(F27:F29) -> 2279250
D32: =D30-'Balanço Contab'!D33 -> 0 | E32: =E30-'Balanço Contab'!E33 -> 0 | F32: =F30-'Balanço Contab'!F33 -> 0

Sheet DFC
A1: Entidade: | B1: JJ Teixeira, S.A.
B2: Wood Engineeing Tailor
B4: Demonstração dos Fluxos de Caixa a 31 de dezembro | F4: (em euros)
C5: Notas | D5: Anos
D6: 2022 | E6: 2023 | F6: 2024
B7: ATIVIDADES OPERACIONAIS
B8: Recebimentos de Clientes | D8: 32022238 | E8: 35414144 | F8: 33078927
B9: Pagamentos a Fornecedores | D9: -20413424 | E9: -20834983 | F9: -29115362
B10: Pagamentos ao Pessoal | D10: -7735883.1 | E10: -8212829 | F10: -5083582
B11: Fluxo de caixa gerado pelas operações | D11: =SUM(D8:D10) -> 3872930.9 | E11: =SUM(E8:E10) -> 6366332 | F11: =SUM(F8:F10) -> -1120017
B12: Pagamento/Recebimento do imposto sobre o valor acrescentado
B13: Pagamento/Recebimento do imposto sobre o rendimento | D13: -14353 | E13: -36916 | F13: -31714
B14: Outros recebimentos/pagamentos | D14: -890155 | E14: -1479222 | F14: -987583
B15: FLUXO GERADO PELAS ATIVIDADES OPERACIONAIS | D15: =SUM(D11:D14) -> 2968422.9 | E15: =SUM(E11:E14) -> 4850194 | F15: =SUM(F11:F14) -> -2139314
B17: ATIVIDADES DE INVESTIMENTO
B18: Pagamentos de:
B19: - Ativos Fixos Tangíveis | D19: -677259 | E19: -1361396 | F19: -2496379
B20: - Ativos Fixos Intangíveis
B21: - Investimentos Financeiros
B22: - Outros Ativos
B23: - Subsídios ao Investimento
B25: Recebimentos de:
B26: - Ativos Fixos Tangíveis | D26: 216000
B27: - Ativos Fixos Intangíveis
B28: - Investimentos Financeiros | D28: 99
B29: - Outros Ativos
B30: - Subsídios ao Investimento | D30: 693 | E30: 611
B31: - Juros e Rendimentos similares
B32: - Dividendos
B33: FLUXO GERADO PELAS ATIVIDADES INVESTIMENTO | D33: =SUM(D19:D32) -> -460467 | E33: =SUM(E19:E32) -> -1360785 | F33: =SUM(F19:F32) -> -2496379
B35: ATIVIDADES DE FINANCIAMENTO
B36: Recebimentos de:
B37: - Financiamentos Obtidos | D37: 9560728 | E37: 8828515 | F37: 34670956
B38: - Realizações de capital e de outros instrumentos de Capital Próprio
B39: - Cobertura de Prejuízos
B40: - Doações
B41: - Juros e rendimentos similares
B42: - Outras operações de financiamento
B44: Pagamentos de:
B45: - Financiamentos Obtidos | D45: -10675529 | E45: -9433377 | F45: -31319779
B46: - Juros e gastos similares | D46: -597182 | E46: -1004232 | F46: -1054027
B47: - Dividendos
B48: - Reduções de Capital e de outros instrumentos de Capital Próprio
B49: - Aquisições de Ações Próprias
B50: - Outras operações financiamento
B51: FLUXO GERADO PELAS ATIVIDADES FINANCIAMENTO | D51: =SUM(D37:D50) -> -1711983 | E51: =SUM(E37:E50) -> -1609094 | F51: =SUM(F37:F50) -> 2297150.5
B53: VARIAÇÃO de CAIXA e EQUIVALENTES | D53: =D15+D33+D51 -> 795972.9 | E53: =E15+E33+E51 -> 1880315 | F53: =F15+F33+F51 -> -2338542.5
B54: Efeito das diferenças de câmbio | E54: 171
B55: CAIXA e EQUIVALENTES no ÍNICIO do PERÍODO | D55: 1461954 | E55: 2257926.9 | F55: 4138412.9
B56: CAIXA e EQUIVALENTES no FIM do PERÍODO | D56: =SUM(D53:D55) -> 2257926.9 | E56: =SUM(E53:E55) -> 4138412.9 | F56: =SUM(F53:F55) -> 1799870.4
D58: =D56-'Balanço Contab'!D22 -> -0.1 | E58: =E56-'Balanço Contab'!E22 -> -0.1 | F58: =F56-'Balanço Contab'!F22 -> 0.4

Sheet Técnicas
A2: Entidade: | B2: JJ Teixeira, S.A.
B4: Balanço individual a 31 de dezembro | D4: Numeros Índice Base Móvel = (rubrica / ano anterior) x 100 | H4: Mapa de Mutação de Valores | K4: Balanço individual a 31 de dezembro | R4: Valores Relativos | U4: Balanço individual a 31 de dezembro | AB4: Índices de Base Fixa (IBF) | AE4: Balanço individual a 31 de dezembro | AL4: Índices de Base Móvel (IBM)
B5: Rubricas | C5: Notas | D5: Anos | G5: Valores Absolutos (€) | K5: Rubricas | L5: Notas | M5: 2022 | O5: 2023 | Q5: 2024 | U5: Rubricas | V5: Notas | W5: 2022 | Y5: 2023 | AA5: 2024 | AE5: Rubricas | AF5: Notas | AG5: 2022 | AI5: 2023 | AK5: 2024
D6: 2022 | E6: 2023 | F6: 2024 | G6: (2023) - (2022) | H6: (2024) - (2023) | M6: Valor (€) | N6: % | O6: Valor (€) | P6: % | Q6: Valor (€) | R6: % | W6: Valor (€) | X6: IBF | Y6: Valor (€) | Z6: IBF | AA6: Valor (€) | AB6: IBF | AG6: Valor (€) | AH6: IBM | AI6: Valor (€) | AJ6: IBM | AK6: Valor (€) | AL6: IBM
B7: ='Balanço Contab'!B7 -> ATIVO | K7: =B7 -> ATIVO | U7: =K7 -> ATIVO | AE7: =U7 -> ATIVO
B8: ='Balanço Contab'!B8 -> Ativo não corrente | K8: =B8 -> Ativo não corrente | U8: =K8 -> Ativo não corrente | AE8: =U8 -> Ativo não corrente
B9: ='Balanço Contab'!B9 -> Ativos fixos tangíveis | D9: ='Balanço Contab'!D9 -> 19459800 | E9: ='Balanço Contab'!E9 -> 18666572 | F9: ='Balanço Contab'!F9 -> 20729866 | G9: =E9-D9 -> -793228.5 | H9: =F9-E9 -> 2063294 | K9: =B9 -> Ativos fixos tangíveis | M9: =D9 -> 19459800 | N9: =M9/$M$24 -> 0.44350645 | O9: =E9 -> 18666572 | P9: =O9/$O$24 -> 0.3893929 | Q9: =F9 -> 20729866 | R9: =Q9/$Q$24 -> 0.39809873 | U9: =B9 -> Ativos fixos tangíveis | W9: =D9 -> 19459800 | X9: =(W9/W9)*100 -> 100 | Y9: =E9 -> 18666572 | Z9: =(Y9/W9)*100 -> 95.923758 | AA9: =F9 -> 20729866 | AB9: =(AA9/W9)*100 -> 106.52661 | AE9: =B9 -> Ativos fixos tangíveis | AG9: =D9 -> 19459800 | AH9: =(AG9/AG9)*100 -> 100 | AI9: =E9 -> 18666572 | AJ9: =(AI9/AG9)*100 -> 95.923758 | AK9: =F9 -> 20729866 | AL9: =(AK9/AI9)*100 -> 111.05342
B10: ='Balanço Contab'!B10 -> Propriedades de investimento | D10: ='Balanço Contab'!D10 -> 78216 | E10: ='Balanço Contab'!E10 -> 76393 | F10: ='Balanço Contab'!F10 -> 74571 | G10: =E10-D10 -> -1823 | H10: =F10-E10 -> -1822 | K10: =B10 -> Propriedades de investimento | M10: =D10 -> 78216 | N10: =M10/$M$24 -> 0.0017826134 | O10: =E10 -> 76393 | P10: =O10/$O$24 -> 0.0015935916 | Q10: =F10 -> 74571 | R10: =Q10/$Q$24 -> 0.0014320701 | U10: =B10 -> Propriedades de investimento | W10: =D10 -> 78216 | X10: =(W10/W10)*100 -> 100 | Y10: =E10 -> 76393 | Z10: =(Y10/W10)*100 -> 97.669275 | AA10: =F10 -> 74571 | AB10: =(AA10/W10)*100 -> 95.339828 | AE10: =B10 -> Propriedades de investimento | AG10: =D10 -> 78216 | AH10: =(AG10/AG10)*100 -> 100 | AI10: =E10 -> 76393 | AJ10: =(AI10/AG10)*100 -> 97.669275 | AK10: =F10 -> 74571 | AL10: =(AK10/AI10)*100 -> 97.614965
B11: ='Balanço Contab'!B11 -> Ativos intangíveis | D11: ='Balanço Contab'!D11 -> 278210 | E11: ='Balanço Contab'!E11 -> 261041 | F11: ='Balanço Contab'!F11 -> 242369 | G11: =E11-D11 -> -17169 | H11: =F11-E11 -> -18672 | K11: =B11 -> Ativos intangíveis | M11: =D11 -> 278210 | N11: =M11/$M$24 -> 0.0063406577 | O11: =E11 -> 261041 | P11: =O11/$O$24 -> 0.0054454302 | Q11: =F11 -> 242369 | R11: =Q11/$Q$24 -> 0.0046544822 | U11: =B11 -> Ativos intangíveis | W11: =D11 -> 278210 | X11: =(W11/W11)*100 -> 100 | Y11: =E11 -> 261041 | Z11: =(Y11/W11)*100 -> 93.828762 | AA11: =F11 -> 242369 | AB11: =(AA11/W11)*100 -> 87.117286 | AE11: =B11 -> Ativos intangíveis | AG11: =D11 -> 278210 | AH11: =(AG11/AG11)*100 -> 100 | AI11: =E11 -> 261041 | AJ11: =(AI11/AG11)*100 -> 93.828762 | AK11: =F11 -> 242369 | AL11: =(AK11/AI11)*100 -> 92.847101
B12: ='Balanço Contab'!B12 -> Participações financeiras - Outros métodos | D12: ='Balanço Contab'!D12 -> 160000 | E12: ='Balanço Contab'!E12 -> 166000 | F12: ='Balanço Contab'!F12 -> 166000 | G12: =E12-D12 -> 6000 | H12: =F12-E12 -> 0 | K12: =B12 -> Participações financeiras - Outros métodos | M12: =D12 -> 160000 | N12: =M12/$M$24 -> 0.0036465448 | O12: =E12 -> 166000 | P12: =O12/$O$24 -> 0.0034628331 | Q12: =F12 -> 166000 | R12: =Q12/$Q$24 -> 0.0031878832 | U12: =B12 -> Participações financeiras - Outros métodos | W12: =D12 -> 160000 | X12: =(W12/W12)*100 -> 100 | Y12: =E12 -> 166000 | Z12: =(Y12/W12)*100 -> 103.75 | AA12: =F12 -> 166000 | AB12: =(AA12/W12)*100 -> 103.75 | AE12: =B12 -> Participações financeiras - Outros métodos | AG12: =D12 -> 160000 | AH12: =(AG12/AG12)*100 -> 100 | AI12: =E12 -> 166000 | AJ12: =(AI12/AG12)*100 -> 103.75 | AK12: =F12 -> 166000 | AL12: =(AK12/AI12)*100 -> 100
B13: ='Balanço Contab'!B13 -> Outros ativos financeiros | D13: ='Balanço Contab'!D13 -> 2392 | E13: ='Balanço Contab'!E13 -> 2944 | F13: ='Balanço Contab'!F13 -> 2887 | G13: =E13-D13 -> 552 | H13: =F13-E13 -> -57 | K13: =B13 -> Outros ativos financeiros | M13: =D13 -> 2392 | N13: =M13/$M$24 -> 5.4515845e-05 | O13: =E13 -> 2944 | P13: =O13/$O$24 -> 6.1413136e-05 | Q13: =F13 -> 2887 | R13: =Q13/$Q$24 -> 5.5442281e-05 | U13: =B13 -> Outros ativos financeiros | W13: =D13 -> 2392 | X13: =(W13/W13)*100 -> 100 | Y13: =E13 -> 2944 | Z13: =(Y13/W13)*100 -> 123.07692 | AA13: =F13 -> 2887 | AB13: =(AA13/W13)*100 -> 120.69398 | AE13: =B13 -> Outros ativos financeiros | AG13: =D13 -> 2392 | AH13: =(AG13/AG13)*100 -> 100 | AI13: =E13 -> 2944 | AJ13: =(AI13/AG13)*100 -> 123.07692 | AK13: =F13 -> 2887 | AL13: =(AK13/AI13)*100 -> 98.063859
B14: ='Balanço Contab'!B14 -> Ativos por impostos diferidos | D14: ='Balanço Contab'!D14 -> 3543112 | E14: ='Balanço Contab'!E14 -> 2870650 | F14: ='Balanço Contab'!F14 -> 3308871 | G14: =E14-D14 -> -672462 | H14: =F14-E14 -> 438221 | K14: =B14 -> Ativos por impostos diferidos | M14: =D14 -> 3543112 | N14: =M14/$M$24 -> 0.080750729 | O14: =E14 -> 2870650 | P14: =O14/$O$24 -> 0.059883023 | Q14: =F14 -> 3308871 | R14: =Q14/$Q$24 -> 0.063543941 | U14: =B14 -> Ativos por impostos diferidos | W14: =D14 -> 3543112 | X14: =(W14/W14)*100 -> 100 | Y14: =E14 -> 2870650 | Z14: =(Y14/W14)*100 -> 81.020583 | AA14: =F14 -> 3308871 | AB14: =(AA14/W14)*100 -> 93.388834 | AE14: =B14 -> Ativos por impostos diferidos | AG14: =D14 -> 3543112 | AH14: =(AG14/AG14)*100 -> 100 | AI14: =E14 -> 2870650 | AJ14: =(AI14/AG14)*100 -> 81.020583 | AK14: =F14 -> 3308871 | AL14: =(AK14/AI14)*100 -> 115.26557
D15: =SUM(D9:D14) -> 23521730 | E15: =SUM(E9:E14) -> 22043600 | F15: =SUM(F9:F14) -> 24524564 | G15: =E15-D15 -> -1478130.5 | H15: =F15-E15 -> 2480964 | M15: =SUM(M9:M14) -> 23521730 | N15: =M15/$M$24 -> 0.53608151 | O15: =SUM(O9:O14) -> 22043600 | P15: =O15/$O$24 -> 0.45983919 | Q15: =SUM(Q9:Q14) -> 24524564 | R15: =Q15/$Q$24 -> 0.47097255 | W15: =SUM(W9:W14) -> 23521730 | X15: =(W15/W15)*100 -> 100 | Y15: =SUM(Y9:Y14) -> 22043600 | Z15: =(Y15/W15)*100 -> 93.715894 | AA15: =SUM(AA9:AA14) -> 24524564 | AB15: =(AA15/W15)*100 -> 104.26343 | AG15: =SUM(AG9:AG14) -> 23521730 | AH15: =(AG15/AG15)*100 -> 100 | AI15: =SUM(AI9:AI14) -> 22043600 | AJ15: =(AI15/AG15)*100 -> 93.715894 | AK15: =SUM(AK9:AK14) -> 24524564 | AL15: =(AK15/AI15)*100 -> 111.2548
B16: ='Balanço Contab'!B16 -> Ativo corrente | K16: =B16 -> Ativo corrente | N16: =M16/$M$24 -> 0 | P16: =O16/$O$24 -> 0 | R16: =Q16/$Q$24 -> 0 | U16: =K16 -> Ativo corrente | AE16: =U16 -> Ativo corrente
B17: ='Balanço Contab'!B17 -> Inventários | D17: ='Balanço Contab'!D17 -> 2476629 | E17: ='Balanço Contab'!E17 -> 2368546 | F17: ='Balanço Contab'!F17 -> 2667287 | G17: =E17-D17 -> -108083 | H17: =F17-E17 -> 298741 | K17: =B17 -> Inventários | M17: =D17 -> 2476629 | N17: =M17/$M$24 -> 0.056444616 | O17: =E17 -> 2368546 | P17: =O17/$O$24 -> 0.049408912 | Q17: =F17 -> 2667287 | R17: =Q17/$Q$24 -> 0.051222887 | U17: =B17 -> Inventários | W17: =D17 -> 2476629 | X17: =(W17/W17)*100 -> 100 | Y17: =E17 -> 2368546 | Z17: =(Y17/W17)*100 -> 95.635882 | AA17: =F17 -> 2667287 | AB17: =(AA17/W17)*100 -> 107.69829 | AE17: =B17 -> Inventários | AG17: =D17 -> 2476629 | AH17: =(AG17/AG17)*100 -> 100 | AI17: =E17 -> 2368546 | AJ17: =(AI17/AG17)*100 -> 95.635882 | AK17: =F17 -> 2667287 | AL17: =(AK17/AI17)*100 -> 112.61284
B18: ='Balanço Contab'!B18 -> Clientes | D18: ='Balanço Contab'!D18 -> 10993343 | E18: ='Balanço Contab'!E18 -> 13433628 | F18: ='Balanço Contab'!F18 -> 15033498 | G18: =E18-D18 -> 2440284.5 | H18: =F18-E18 -> 1599871 | K18: =B18 -> Clientes | M18: =D18 -> 10993343 | N18: =M18/$M$24 -> 0.25054824 | O18: =E18 -> 13433628 | P18: =O18/$O$24 -> 0.28023138 | Q18: =F18 -> 15033498 | R18: =Q18/$Q$24 -> 0.28870504 | U18: =B18 -> Clientes | W18: =D18 -> 10993343 | X18: =(W18/W18)*100 -> 100 | Y18: =E18 -> 13433628 | Z18: =(Y18/W18)*100 -> 122.19784 | AA18: =F18 -> 15033498 | AB18: =(AA18/W18)*100 -> 136.75093 | AE18: =U18 -> Clientes | AG18: =D18 -> 10993343 | AH18: =(AG18/AG18)*100 -> 100 | AI18: =E18 -> 13433628 | AJ18: =(AI18/AG18)*100 -> 122.19784 | AK18: =F18 -> 15033498 | AL18: =(AK18/AI18)*100 -> 111.90945
B19: ='Balanço Contab'!B19 -> Estado e Outros Entes Públicos | D19: ='Balanço Contab'!D19 -> 299077 | E19: ='Balanço Contab'!E19 -> 254510 | F19: ='Balanço Contab'!F19 -> 764059 | G19: =E19-D19 -> -44567 | H19: =F19-E19 -> 509549 | K19: =B19 -> Estado e Outros Entes Públicos | M19: =D19 -> 299077 | N19: =M19/$M$24 -> 0.0068162355 | O19: =E19 -> 254510 | P19: =O19/$O$24 -> 0.0053091906 | Q19: =F19 -> 764059 | R19: =Q19/$Q$24 -> 0.014673077 | U19: =B19 -> Estado e Outros Entes Públicos | W19: =D19 -> 299077 | X19: =(W19/W19)*100 -> 100 | Y19: =E19 -> 254510 | Z19: =(Y19/W19)*100 -> 85.098486 | AA19: =F19 -> 764059 | AB19: =(AA19/W19)*100 -> 255.47234 | AE19: =U19 -> Estado e Outros Entes Públicos | AG19: =D19 -> 299077 | AH19: =(AG19/AG19)*100 -> 100 | AI19: =E19 -> 254510 | AJ19: =(AI19/AG19)*100 -> 85.098486 | AK19: =F19 -> 764059 | AL19: =(AK19/AI19)*100 -> 300.20785
B20: ='Balanço Contab'!B20 -> Outros créditos a receber | D20: ='Balanço Contab'!D20 -> 4152529 | E20: ='Balanço Contab'!E20 -> 5511417 | F20: ='Balanço Contab'!F20 -> 7076559 | G20: =E20-D20 -> 1358888 | H20: =F20-E20 -> 1565142 | K20: =B20 -> Outros créditos a receber | M20: =D20 -> 4152529 | N20: =M20/$M$24 -> 0.094639894 | O20: =E20 -> 5511417 | P20: =O20/$O$24 -> 0.11497058 | Q20: =F20 -> 7076559 | R20: =Q20/$Q$24 -> 0.13589906 | U20: =B20 -> Outros créditos a receber | W20: =D20 -> 4152529 | X20: =(W20/W20)*100 -> 100 | Y20: =E20 -> 5511417 | Z20: =(Y20/W20)*100 -> 132.72435 | AA20: =F20 -> 7076559 | AB20: =(AA20/W20)*100 -> 170.41564 | AE20: =U20 -> Outros créditos a receber | AG20: =D20 -> 4152529 | AH20: =(AG20/AG20)*100 -> 100 | AI20: =E20 -> 5511417 | AJ20: =(AI20/AG20)*100 -> 132.72435 | AK20: =F20 -> 7076559 | AL20: =(AK20/AI20)*100 -> 128.39818
B21: ='Balanço Contab'!B21 -> Diferimentos | D21: ='Balanço Contab'!D21 -> 175917 | E21: ='Balanço Contab'!E21 -> 187514 | F21: ='Balanço Contab'!F21 -> 206335 | G21: =E21-D21 -> 11597 | H21: =F21-E21 -> 18821 | K21: =B21 -> Diferimentos | M21: =D21 -> 175917 | N21: =M21/$M$24 -> 0.0040093076 | O21: =E21 -> 187514 | P21: =O21/$O$24 -> 0.0039116246 | Q21: =F21 -> 206335 | R21: =Q21/$Q$24 -> 0.0039624812 | U21: =B21 -> Diferimentos | W21: =D21 -> 175917 | X21: =(W21/W21)*100 -> 100 | Y21: =E21 -> 187514 | Z21: =(Y21/W21)*100 -> 106.59231 | AA21: =F21 -> 206335 | AB21: =(AA21/W21)*100 -> 117.29111 | AE21: =U21 -> Diferimentos | AG21: =D21 -> 175917 | AH21: =(AG21/AG21)*100 -> 100 | AI21: =E21 -> 187514 | AJ21: =(AI21/AG21)*100 -> 106.59231 | AK21: =F21 -> 206335 | AL21: =(AK21/AI21)*100 -> 110.03712
B22: ='Balanço Contab'!B22 -> Caixa e depósitos bancários | D22: ='Balanço Contab'!D22 -> 2257927 | E22: ='Balanço Contab'!E22 -> 4138413 | F22: ='Balanço Contab'!F22 -> 1799870 | G22: =E22-D22 -> 1880486 | H22: =F22-E22 -> -2338543 | K22: =B22 -> Caixa e depósitos bancários | M22: =D22 -> 2257927 | N22: =M22/$M$24 -> 0.0514602 | O22: =E22 -> 4138413 | P22: =O22/$O$24 -> 0.086329117 | Q22: =F22 -> 1799870 | R22: =Q22/$Q$24 -> 0.034564911 | U22: =B22 -> Caixa e depósitos bancários | W22: =D22 -> 2257927 | X22: =(W22/W22)*100 -> 100 | Y22: =E22 -> 4138413 | Z22: =(Y22/W22)*100 -> 183.28374 | AA22: =F22 -> 1799870 | AB22: =(AA22/W22)*100 -> 79.713383 | AE22: =U22 -> Caixa e depósitos bancários | AG22: =D22 -> 2257927 | AH22: =(AG22/AG22)*100 -> 100 | AI22: =E22 -> 4138413 | AJ22: =(AI22/AG22)*100 -> 183.28374 | AK22: =F22 -> 1799870 | AL22: =(AK22/AI22)*100 -> 43.491793
D23: =SUM(D17:D22) -> 20355422 | E23: =SUM(E17:E22) -> 25894028 | F23: =SUM(F17:F22) -> 27547608 | G23: =E23-D23 -> 5538605.5 | H23: =F23-E23 -> 1653581 | M23: =SUM(M17:M22) -> 20355422 | N23: =M23/$M$24 -> 0.46391849 | O23: =SUM(O17:O22) -> 25894028 | P23: =O23/$O$24 -> 0.54016081 | Q23: =SUM(Q17:Q22) -> 27547608 | R23: =Q23/$Q$24 -> 0.52902745 | W23: =SUM(W17:W22) -> 20355422 | X23: =(W23/W23)*100 -> 100 | Y23: =SUM(Y17:Y22) -> 25894028 | Z23: =(Y23/W23)*100 -> 127.20949 | AA23: =SUM(AA17:AA22) -> 27547608 | AB23: =(AA23/W23)*100 -> 135.33303 | AG23: =SUM(AG17:AG22) -> 20355422 | AH23: =(AG23/AG23)*100 -> 100 | AI23: =SUM(AI17:AI22) -> 25894028 | AJ23: =(AI23/AG23)*100 -> 127.20949 | AK23: =SUM(AK17:AK22) -> 27547608 | AL23: =(AK23/AI23)*100 -> 106.38596
B24: ='Balanço Contab'!B24 -> Total do Ativo | D24: =D15+D23 -> 43877152 | E24: =E15+E23 -> 47937627 | F24: =F15+F23 -> 52072172 | G24: =E24-D24 -> 4060475 | H24: =F24-E24 -> 4134545 | K24: =B24 -> Total do Ativo | M24: =M15+M23 -> 43877152 | N24: =M24/$M$24 -> 1 | O24: =O15+O23 -> 47937627 | P24: =O24/$O$24 -> 1 | Q24: =Q15+Q23 -> 52072172 | R24: =Q24/$Q$24 -> 1 | U24: =K24 -> Total do Ativo | W24: =W15+W23 -> 43877152 | X24: =(W24/W24)*100 -> 100 | Y24: =Y15+Y23 -> 47937627 | Z24: =(Y24/W24)*100 -> 109.25419 | AA24: =AA15+AA23 -> 52072172 | AB24: =(AA24/W24)*100 -> 118.67719 | AE24: =U24 -> Total do Ativo | AG24: =AG15+AG23 -> 43877152 | AH24: =(AG24/AG24)*100 -> 100 | AI24: =AI15+AI23 -> 47937627 | AJ24: =(AI24/AG24)*100 -> 109.25419 | AK24: =AK15+AK23 -> 52072172 | AL24: =(AK24/AI24)*100 -> 108.62484
B25: Rubricas | C25: Notas | D25: Anos | G25: Valores Absolutos (€) | K25: Rubricas | L25: Notas | M25: 2022 | O25: 2023 | Q25: 2024 | U25: Rubricas | V25: Notas | W25: 2022 | Y25: 2023 | AA25: 2024 | AE25: Rubricas | AF25: Notas | AG25: 2022 | AI25: 2023 | AK25: 2024
D26: 2022 | E26: 2023 | F26: 2024 | G26: (2023) - (2022) | H26: (2024) - (2023) | M26: Valor (€) | N26: % | O26: Valor (€) | P26: % | Q26: Valor (€) | R26: % | W26: Valor (€) | X26: IBF | Y26: Valor (€) | Z26: IBF | AA26: Valor (€) | AB26: IBF | AG26: Valor (€) | AH26: IBM | AI26: Valor (€) | AJ26: IBM | AK26: Valor (€) | AL26: IBM
B27: ='Balanço Contab'!B25 -> CAPITAL PRÓPRIO PASSIVO | K27: =B27 -> CAPITAL PRÓPRIO PASSIVO | U27: =K27 -> CAPITAL PRÓPRIO PASSIVO | AE27: =U27 -> CAPITAL PRÓPRIO PASSIVO
B28: ='Balanço Contab'!B26 -> Capital Próprio | K28: =B28 -> Capital Próprio | U28: =K28 -> Capital Próprio | AE28: =U28 -> Capital Próprio
B29: ='Balanço Contab'!B27 -> Capital realizado | D29: ='Balanço Contab'!D27 -> 11740455 | E29: ='Balanço Contab'!E27 -> 11740455 | F29: ='Balanço Contab'!F27 -> 11740455 | G29: =E29-D29 -> 0 | H29: =F29-E29 -> 0 | K29: =B29 -> Capital realizado | M29: =D29 -> 11740455 | N29: =M29/$M$53 -> 0.26757559 | O29: =E29 -> 11740455 | P29: =O29/$O$53 -> 0.24491106 | Q29: =F29 -> 11740455 | R29: =Q29/$Q$53 -> 0.22546505 | U29: =B29 -> Capital realizado | W29: =D29 -> 11740455 | X29: =(W29/W29)*100 -> 100 | Y29: =E29 -> 11740455 | Z29: =(Y29/W29)*100 -> 100 | AA29: =F29 -> 11740455 | AB29: =(AA29/W29)*100 -> 100 | AE29: =B29 -> Capital realizado | AG29: =D29 -> 11740455 | AH29: =(AG29/AG29)*100 -> 100 | AI29: =E29 -> 11740455 | AJ29: =(AI29/AG29)*100 -> 100 | AK29: =F29 -> 11740455 | AL29: =(AK29/AI29)*100 -> 100
B30: ='Balanço Contab'!B28 -> Prémios de emissão | D30: ='Balanço Contab'!D28 -> 959545 | E30: ='Balanço Contab'!E28 -> 959545 | F30: ='Balanço Contab'!F28 -> 959545 | G30: =E30-D30 -> 0 | H30: =F30-E30 -> 0 | K30: =B30 -> Prémios de emissão | M30: =D30 -> 959545 | N30: =M30/$M$53 -> 0.021868899 | O30: =E30 -> 959545 | P30: =O30/$O$53 -> 0.020016531 | Q30: =F30 -> 959545 | R30: =Q30/$Q$53 -> 0.018427213 | U30: =B30 -> Prémios de emissão | W30: =D30 -> 959545 | X30: =(W30/W30)*100 -> 100 | Y30: =E30 -> 959545 | Z30: =(Y30/W30)*100 -> 100 | AA30: =F30 -> 959545 | AB30: =(AA30/W30)*100 -> 100 | AE30: =B30 -> Prémios de emissão | AG30: =D30 -> 959545 | AH30: =(AG30/AG30)*100 -> 100 | AI30: =E30 -> 959545 | AJ30: =(AI30/AG30)*100 -> 100 | AK30: =F30 -> 959545 | AL30: =(AK30/AI30)*100 -> 100
B31: ='Balanço Contab'!B29 -> Reservas Legais | D31: ='Balanço Contab'!D29 -> 658278 | E31: ='Balanço Contab'!E29 -> 773685 | F31: ='Balanço Contab'!F29 -> 891080 | G31: =E31-D31 -> 115407 | H31: =F31-E31 -> 117395 | K31: =B31 -> Reservas Legais | M31: =D31 -> 658278 | N31: =M31/$M$53 -> 0.015002751 | O31: =E31 -> 773685 | P31: =O31/$O$53 -> 0.01613941 | Q31: =F31 -> 891080 | R31: =Q31/$Q$53 -> 0.017112403 | U31: =B31 -> Reservas Legais | W31: =D31 -> 658278 | X31: =(W31/W31)*100 -> 100 | Y31: =E31 -> 773685 | Z31: =(Y31/W31)*100 -> 117.53165 | AA31: =F31 -> 891080 | AB31: =(AA31/W31)*100 -> 135.3653 | AE31: =B31 -> Reservas Legais | AG31: =D31 -> 658278 | AH31: =(AG31/AG31)*100 -> 100 | AI31: =E31 -> 773685 | AJ31: =(AI31/AG31)*100 -> 117.53165 | AK31: =F31 -> 891080 | AL31: =(AK31/AI31)*100 -> 115.17349
B32: ='Balanço Contab'!B30 -> Outras reservas | D32: ='Balanço Contab'!D30 -> 4710221 | E32: ='Balanço Contab'!E30 -> 4710221 | F32: ='Balanço Contab'!F30 -> 4710221 | G32: =E32-D32 -> 0 | H32: =F32-E32 -> 0 | K32: =B32 -> Outras reservas | M32: =D32 -> 4710221 | N32: =M32/$M$53 -> 0.1073502 | O32: =E32 -> 4710221 | P32: =O32/$O$53 -> 0.098257283 | Q32: =F32 -> 4710221 | R32: =Q32/$Q$53 -> 0.090455628 | U32: =B32 -> Outras reservas | W32: =D32 -> 4710221 | X32: =(W32/W32)*100 -> 100 | Y32: =E32 -> 4710221 | Z32: =(Y32/W32)*100 -> 100 | AA32: =F32 -> 4710221 | AB32: =(AA32/W32)*100 -> 100 | AE32: =B32 -> Outras reservas | AG32: =D32 -> 4710221 | AH32: =(AG32/AG32)*100 -> 100 | AI32: =E32 -> 4710221 | AJ32: =(AI32/AG32)*100 -> 100 | AK32: =F32 -> 4710221 | AL32: =(AK32/AI32)*100 -> 100
B33: ='Balanço Contab'!B31 -> Resultados Transitados | D33: ='Balanço Contab'!D31 -> -2266539 | E33: ='Balanço Contab'!E31 -> -73815 | F33: ='Balanço Contab'!F31 -> 2156686 | G33: =E33-D33 -> 2192724 | H33: =F33-E33 -> 2230501 | K33: =B33 -> Resultados Transitados | M33: =D33 -> -2266539 | N33: =M33/$M$53 -> -0.051656475 | O33: =E33 -> -73815 | P33: =O33/$O$53 -> -0.0015398134 | Q33: =F33 -> 2156686 | R33: =Q33/$Q$53 -> 0.041417247 | U33: =B33 -> Resultados Transitados | W33: =D33 -> -2266539 | X33: =(W33/W33)*100 -> 100 | Y33: =E33 -> -73815 | AA33: =F33 -> 2156686 | AE33: =B33 -> Resultados Transitados | AG33: =D33 -> -2266539 | AH33: =(AG33/AG33)*100 -> 100 | AI33: =E33 -> -73815 | AK33: =F33 -> 2156686
B34: ='Balanço Contab'!B32 -> Outras variações no capital próprio | D34: ='Balanço Contab'!D32 -> 2482464 | E34: ='Balanço Contab'!E32 -> 1982771 | F34: ='Balanço Contab'!F32 -> 1622563 | G34: =E34-D34 -> -499693 | H34: =F34-E34 -> -360208 | K34: =B34 -> Outras variações no capital próprio | M34: =D34 -> 2482464 | N34: =M34/$M$53 -> 0.056577601 | O34: =E34 -> 1982771 | P34: =O34/$O$53 -> 0.041361476 | Q34: =F34 -> 1622563 | R34: =Q34/$Q$53 -> 0.031159887 | U34: =B34 -> Outras variações no capital próprio | W34: =D34 -> 2482464 | X34: =(W34/W34)*100 -> 100 | Y34: =E34 -> 1982771 | Z34: =(Y34/W34)*100 -> 79.871088 | AA34: =F34 -> 1622563 | AB34: =(AA34/W34)*100 -> 65.360988 | AE34: =B34 -> Outras variações no capital próprio | AG34: =D34 -> 2482464 | AH34: =(AG34/AG34)*100 -> 100 | AI34: =E34 -> 1982771 | AJ34: =(AI34/AG34)*100 -> 79.871088 | AK34: =F34 -> 1622563 | AL34: =(AK34/AI34)*100 -> 81.833101
B35: ='Balanço Contab'!B33 -> Resultado liquido do período | D35: ='Balanço Contab'!D33 -> 2308131 | E35: ='Balanço Contab'!E33 -> 2347896 | F35: ='Balanço Contab'!F33 -> 2279250 | G35: =E35-D35 -> 39765 | H35: =F35-E35 -> -68646 | K35: =B35 -> Resultado liquido do período | M35: =D35 -> 2308131 | N35: =M35/$M$53 -> 0.052604394 | O35: =E35 -> 2347896 | P35: =O35/$O$53 -> 0.048978144 | Q35: =F35 -> 2279250 | R35: =Q35/$Q$53 -> 0.04377098 | U35: =B35 -> Resultado liquido do período | W35: =D35 -> 2308131 | X35: =(W35/W35)*100 -> 100 | Y35: =E35 -> 2347896 | Z35: =(Y35/W35)*100 -> 101.72282 | AA35: =F35 -> 2279250 | AB35: =(AA35/W35)*100 -> 98.748728 | AE35: =B35 -> Resultado liquido do período | AG35: =D35 -> 2308131 | AH35: =(AG35/AG35)*100 -> 100 | AI35: =E35 -> 2347896 | AJ35: =(AI35/AG35)*100 -> 101.72282 | AK35: =F35 -> 2279250 | AL35: =(AK35/AI35)*100 -> 97.076276
B36: ='Balanço Contab'!B34 -> Total do Capital Próprio | D36: =SUM(D29:D35) -> 20592555 | E36: =SUM(E29:E35) -> 22440758 | F36: =SUM(F29:F35) -> 24359800 | G36: =E36-D36 -> 1848203 | H36: =F36-E36 -> 1919042 | K36: =B36 -> Total do Capital Próprio | M36: =SUM(M29:M35) -> 20592555 | N36: =M36/$M$53 -> 0.46932296 | O36: =SUM(O29:O35) -> 22440758 | P36: =O36/$O$53 -> 0.46812409 | Q36: =SUM(Q29:Q35) -> 24359800 | R36: =Q36/$Q$53 -> 0.46780841 | U36: =K36 -> Total do Capital Próprio | W36: =M36 -> 20592555 | X36: =(W36/W36)*100 -> 100 | Y36: =O36 -> 22440758 | Z36: =(Y36/W36)*100 -> 108.9751 | AA36: =Q36 -> 24359800 | AB36: =(AA36/W36)*100 -> 118.29421 | AE36: =U36 -> Total do Capital Próprio | AG36: =SUM(AG29:AG35) -> 20592555 | AH36: =(AG36/AG36)*100 -> 100 | AI36: =SUM(AI29:AI35) -> 22440758 | AJ36: =(AI36/AG36)*100 -> 108.9751 | AK36: =SUM(AK29:AK35) -> 24359800 | AL36: =(AK36/AI36)*100 -> 108.55159
N37: =M37/$M$53 -> 0 | P37: =O37/$O$53 -> 0 | R37: =Q37/$Q$53 -> 0
B38: ='Balanço Contab'!B36 -> Passivo | K38: =B38 -> Passivo | N38: =M38/$M$53 -> 0 | P38: =O38/$O$53 -> 0 | R38: =Q38/$Q$53 -> 0 | U38: =K38 -> Passivo | AE38: =U38 -> Passivo
B39: ='Balanço Contab'!B37 -> Passivo não corrente | K39: =B39 -> Passivo não corrente | N39: =M39/$M$53 -> 0 | P39: =O39/$O$53 -> 0 | R39: =Q39/$Q$53 -> 0 | U39: =K39 -> Passivo não corrente | AE39: =U39 -> Passivo não corrente
B40: ='Balanço Contab'!B38 -> Provisões | D40: ='Balanço Contab'!D38 -> 0 | E40: ='Balanço Contab'!E38 -> 0 | F40: ='Balanço Contab'!F38 -> 0 | G40: =E40-D40 -> 0 | H40: =F40-E40 -> 0 | K40: =B40 -> Provisões | M40: =D40 -> 0 | N40: =M40/$M$53 -> 0 | O40: =E40 -> 0 | P40: =O40/$O$53 -> 0 | Q40: =F40 -> 0 | R40: =Q40/$Q$53 -> 0 | U40: =B40 -> Provisões | W40: =D40 -> 0 | Y40: =E40 -> 0 | AA40: =F40 -> 0 | AE40: =B40 -> Provisões | AG40: =D40 -> 0 | AI40: =E40 -> 0 | AK40: =F40 -> 0
B41: ='Balanço Contab'!B39 -> Financiamentos obtidos | D41: ='Balanço Contab'!D39 -> 10408410 | E41: ='Balanço Contab'!E39 -> 9500813 | F41: ='Balanço Contab'!F39 -> 13988727 | G41: =E41-D41 -> -907597 | H41: =F41-E41 -> 4487914 | K41: =B41 -> Financiamentos obtidos | M41: =D41 -> 10408410 | N41: =M41/$M$53 -> 0.23721708 | O41: =E41 -> 9500813 | P41: =O41/$O$53 -> 0.19819114 | Q41: =F41 -> 13988727 | R41: =Q41/$Q$53 -> 0.26864113 | U41: =B41 -> Financiamentos obtidos | W41: =D41 -> 10408410 | X41: =(W41/W41)*100 -> 100 | Y41: =E41 -> 9500813 | Z41: =(Y41/W41)*100 -> 91.280157 | AA41: =F41 -> 13988727 | AB41: =(AA41/W41)*100 -> 134.39831 | AE41: =B41 -> Financiamentos obtidos | AG41: =D41 -> 10408410 | AH41: =(AG41/AG41)*100 -> 100 | AI41: =E41 -> 9500813 | AJ41: =(AI41/AG41)*100 -> 91.280157 | AK41: =F41 -> 13988727 | AL41: =(AK41/AI41)*100 -> 147.23716
B42: ='Balanço Contab'!B40 -> Outras dívidas a pagar | D42: ='Balanço Contab'!D40 -> 3974890 | E42: ='Balanço Contab'!E40 -> 3334245 | F42: ='Balanço Contab'!F40 -> 1761814 | G42: =E42-D42 -> -640645 | H42: =F42-E42 -> -1572431 | K42: =B42 -> Outras dívidas a pagar | M42: =D42 -> 3974890 | N42: =M42/$M$53 -> 0.09059134 | O42: =E42 -> 3334245 | P42: =O42/$O$53 -> 0.069553818 | Q42: =F42 -> 1761814 | R42: =Q42/$Q$53 -> 0.033834079 | U42: =B42 -> Outras dívidas a pagar | W42: =D42 -> 3974890 | X42: =(W42/W42)*100 -> 100 | Y42: =E42 -> 3334245 | Z42: =(Y42/W42)*100 -> 83.882699 | AA42: =F42 -> 1761814 | AB42: =(AA42/W42)*100 -> 44.323591 | AE42: =B42 -> Outras dívidas a pagar | AG42: =D42 -> 3974890 | AH42: =(AG42/AG42)*100 -> 100 | AI42: =E42 -> 3334245 | AJ42: =(AI42/AG42)*100 -> 83.882699 | AK42: =F42 -> 1761814 | AL42: =(AK42/AI42)*100 -> 52.839968
D43: =SUM(D40:D42) -> 14383300 | E43: =SUM(E40:E42) -> 12835058 | F43: =SUM(F40:F42) -> 15750541 | G43: =E43-D43 -> -1548242 | H43: =F43-E43 -> 2915483 | M43: =SUM(M40:M42) -> 14383300 | N43: =M43/$M$53 -> 0.32780842 | O43: =SUM(O40:O42) -> 12835058 | P43: =O43/$O$53 -> 0.26774496 | Q43: =SUM(Q40:Q42) -> 15750541 | R43: =Q43/$Q$53 -> 0.30247521 | W43: =M43 -> 14383300 | X43: =(W43/W43)*100 -> 100 | Y43: =O43 -> 12835058 | Z43: =(Y43/W43)*100 -> 89.235836 | AA43: =Q43 -> 15750541 | AB43: =(AA43/W43)*100 -> 109.50575 | AG43: =SUM(AG40:AG42) -> 14383300 | AH43: =(AG43/AG43)*100 -> 100 | AI43: =SUM(AI40:AI42) -> 12835058 | AJ43: =(AI43/AG43)*100 -> 89.235836 | AK43: =SUM(AK40:AK42) -> 15750541 | AL43: =(AK43/AI43)*100 -> 122.715
B44: ='Balanço Contab'!B42 -> Passivo Corrente | K44: =B44 -> Passivo Corrente | U44: =K44 -> Passivo Corrente | AE44: =U44 -> Passivo Corrente
B45: ='Balanço Contab'!B43 -> Fornecedores | D45: ='Balanço Contab'!D43 -> 1415895 | E45: ='Balanço Contab'!E43 -> 633029 | F45: ='Balanço Contab'!F43 -> 721181 | G45: =E45-D45 -> -782866 | H45: =F45-E45 -> 88152 | K45: =B45 -> Fornecedores | M45: =D45 -> 1415895 | N45: =M45/$M$53 -> 0.032269528 | O45: =E45 -> 633029 | P45: =O45/$O$53 -> 0.013205264 | Q45: =F45 -> 721181 | R45: =Q45/$Q$53 -> 0.013849643 | U45: =B45 -> Fornecedores | W45: =D45 -> 1415895 | X45: =(W45/W45)*100 -> 100 | Y45: =E45 -> 633029 | Z45: =(Y45/W45)*100 -> 44.708753 | AA45: =F45 -> 721181 | AB45: =(AA45/W45)*100 -> 50.934639 | AE45: =B45 -> Fornecedores | AG45: =D45 -> 1415895 | AH45: =(AG45/AG45)*100 -> 100 | AI45: =E45 -> 633029 | AJ45: =(AI45/AG45)*100 -> 44.708753 | AK45: =F45 -> 721181 | AL45: =(AK45/AI45)*100 -> 113.92543
B46: ='Balanço Contab'!B44 -> Adiantamentos de clientes | D46: ='Balanço Contab'!D44 -> 174400 | E46: ='Balanço Contab'!E44 -> 1889441 | F46: ='Balanço Contab'!F44 -> 1863058 | G46: =E46-D46 -> 1715041 | H46: =F46-E46 -> -26383 | K46: =B46 -> Adiantamentos de clientes | M46: =D46 -> 174400 | N46: =M46/$M$53 -> 0.0039747338 | O46: =E46 -> 1889441 | P46: =O46/$O$53 -> 0.039414571 | Q46: =F46 -> 1863058 | R46: =Q46/$Q$53 -> 0.035778381 | U46: =B46 -> Adiantamentos de clientes | W46: =D46 -> 174400 | X46: =(W46/W46)*100 -> 100 | Y46: =E46 -> 1889441 | Z46: =(Y46/W46)*100 -> 1083.3951 | AA46: =F46 -> 1863058 | AB46: =(AA46/W46)*100 -> 1068.2672 | AE46: =B46 -> Adiantamentos de clientes | AG46: =D46 -> 174400 | AH46: =(AG46/AG46)*100 -> 100 | AI46: =E46 -> 1889441 | AJ46: =(AI46/AG46)*100 -> 1083.3951 | AK46: =F46 -> 1863058 | AL46: =(AK46/AI46)*100 -> 98.603661
B47: ='Balanço Contab'!B45 -> Estado e Outros Entes Públicos | D47: ='Balanço Contab'!D45 -> 425515 | E47: ='Balanço Contab'!E45 -> 408241 | F47: ='Balanço Contab'!F45 -> 400871 | G47: =E47-D47 -> -17274 | H47: =F47-E47 -> -7370 | K47: =B47 -> Estado e Outros Entes Públicos | M47: =D47 -> 425515 | N47: =M47/$M$53 -> 0.0096978719 | O47: =E47 -> 408241 | P47: =O47/$O$53 -> 0.008516087 | Q47: =F47 -> 400871 | R47: =Q47/$Q$53 -> 0.0076983729 | U47: =B47 -> Estado e Outros Entes Públicos | W47: =D47 -> 425515 | X47: =(W47/W47)*100 -> 100 | Y47: =E47 -> 408241 | Z47: =(Y47/W47)*100 -> 95.940449 | AA47: =F47 -> 400871 | AB47: =(AA47/W47)*100 -> 94.20843 | AE47: =B47 -> Estado e Outros Entes Públicos | AG47: =D47 -> 425515 | AH47: =(AG47/AG47)*100 -> 100 | AI47: =E47 -> 408241 | AJ47: =(AI47/AG47)*100 -> 95.940449 | AK47: =F47 -> 400871 | AL47: =(AK47/AI47)*100 -> 98.194694
B48: ='Balanço Contab'!B46 -> Financiamentos Obtidos | D48: ='Balanço Contab'!D46 -> 6052620 | E48: ='Balanço Contab'!E46 -> 8118404 | F48: ='Balanço Contab'!F46 -> 7106798 | G48: =E48-D48 -> 2065784 | H48: =F48-E48 -> -1011606 | K48: =B48 -> Financiamentos Obtidos | M48: =D48 -> 6052620 | N48: =M48/$M$53 -> 0.13794469 | O48: =E48 -> 8118404 | P48: =O48/$O$53 -> 0.16935348 | Q48: =F48 -> 7106798 | R48: =Q48/$Q$53 -> 0.13647977 | U48: =B48 -> Financiamentos Obtidos | W48: =D48 -> 6052620 | X48: =(W48/W48)*100 -> 100 | Y48: =E48 -> 8118404 | Z48: =(Y48/W48)*100 -> 134.13041 | AA48: =F48 -> 7106798 | AB48: =(AA48/W48)*100 -> 117.41689 | AE48: =B48 -> Financiamentos Obtidos | AG48: =D48 -> 6052620 | AH48: =(AG48/AG48)*100 -> 100 | AI48: =E48 -> 8118404 | AJ48: =(AI48/AG48)*100 -> 134.13041 | AK48: =F48 -> 7106798 | AL48: =(AK48/AI48)*100 -> 87.539349
B49: ='Balanço Contab'!B47 -> Outras dívidas a pagar | D49: ='Balanço Contab'!D47 -> 739384 | E49: ='Balanço Contab'!E47 -> 1304192 | F49: ='Balanço Contab'!F47 -> 1772055 | G49: =E49-D49 -> 564808 | H49: =F49-E49 -> 467863 | K49: =B49 -> Outras dívidas a pagar | M49: =D49 -> 739384 | N49: =M49/$M$53 -> 0.01685123 | O49: =E49 -> 1304192 | P49: =O49/$O$53 -> 0.027206019 | Q49: =F49 -> 1772055 | R49: =Q49/$Q$53 -> 0.034030749 | U49: =B49 -> Outras dívidas a pagar | W49: =D49 -> 739384 | X49: =(W49/W49)*100 -> 100 | Y49: =E49 -> 1304192 | Z49: =(Y49/W49)*100 -> 176.38899 | AA49: =F49 -> 1772055 | AB49: =(AA49/W49)*100 -> 239.6664 | AE49: =B49 -> Outras dívidas a pagar | AG49: =D49 -> 739384 | AH49: =(AG49/AG49)*100 -> 100 | AI49: =E49 -> 1304192 | AJ49: =(AI49/AG49)*100 -> 176.38899 | AK49: =F49 -> 1772055 | AL49: =(AK49/AI49)*100 -> 135.87378
B50: ='Balanço Contab'!B48 -> Diferimentos | D50: ='Balanço Contab'!D48 -> 93483 | E50: ='Balanço Contab'!E48 -> 308504 | F50: ='Balanço Contab'!F48 -> 97868 | G50: =E50-D50 -> 215021 | H50: =F50-E50 -> -210636 | K50: =B50 -> Diferimentos | M50: =D50 -> 93483 | N50: =M50/$M$53 -> 0.0021305622 | O50: =E50 -> 308504 | P50: =O50/$O$53 -> 0.0064355292 | Q50: =F50 -> 97868 | R50: =Q50/$Q$53 -> 0.0018794684 | U50: =B50 -> Diferimentos | W50: =D50 -> 93483 | X50: =(W50/W50)*100 -> 100 | Y50: =E50 -> 308504 | Z50: =(Y50/W50)*100 -> 330.0108 | AA50: =F50 -> 97868 | AB50: =(AA50/W50)*100 -> 104.69069 | AE50: =B50 -> Diferimentos | AG50: =D50 -> 93483 | AH50: =(AG50/AG50)*100 -> 100 | AI50: =E50 -> 308504 | AJ50: =(AI50/AG50)*100 -> 330.0108 | AK50: =F50 -> 97868 | AL50: =(AK50/AI50)*100 -> 31.723414
D51: =SUM(D45:D50) -> 8901297 | E51: =SUM(E45:E50) -> 12661811 | F51: =SUM(F45:F50) -> 11961831 | G51: =E51-D51 -> 3760514 | H51: =F51-E51 -> -699980 | M51: =SUM(M45:M50) -> 8901297 | N51: =M51/$M$53 -> 0.20286861 | O51: =SUM(O45:O50) -> 12661811 | P51: =O51/$O$53 -> 0.26413095 | Q51: =SUM(Q45:Q50) -> 11961831 | R51: =Q51/$Q$53 -> 0.22971638 | W51: =M51 -> 8901297 | X51: =(W51/W51)*100 -> 100 | Y51: =O51 -> 12661811 | Z51: =(Y51/W51)*100 -> 142.24681 | AA51: =Q51 -> 11961831 | AB51: =(AA51/W51)*100 -> 134.38301 | AG51: =SUM(AG45:AG50) -> 8901297 | AH51: =(AG51/AG51)*100 -> 100 | AI51: =SUM(AI45:AI50) -> 12661811 | AJ51: =(AI51/AG51)*100 -> 142.24681 | AK51: =SUM(AK45:AK50) -> 11961831 | AL51: =(AK51/AI51)*100 -> 94.471723
B52: ='Balanço Contab'!B50 -> Total do Passivo | D52: =D43+D51 -> 23284597 | E52: =E43+E51 -> 25496869 | F52: =F43+F51 -> 27712372 | G52: =E52-D52 -> 2212272 | H52: =F52-E52 -> 2215503 | K52: =B52 -> Total do Passivo | M52: =M43+M51 -> 23284597 | N52: =M52/$M$53 -> 0.53067704 | O52: =O43+O51 -> 25496869 | P52: =O52/$O$53 -> 0.53187591 | Q52: =Q43+Q51 -> 27712372 | R52: =Q52/$Q$53 -> 0.53219159 | U52: =K52 -> Total do Passivo | W52: =M52 -> 23284597 | X52: =(W52/W52)*100 -> 100 | Y52: =O52 -> 25496869 | Z52: =(Y52/W52)*100 -> 109.50101 | AA52: =Q52 -> 27712372 | AB52: =(AA52/W52)*100 -> 119.0159 | AE52: =U52 -> Total do Passivo | AG52: =AG43+AG51 -> 23284597 | AH52: =(AG52/AG52)*100 -> 100 | AI52: =AI43+AI51 -> 25496869 | AJ52: =(AI52/AG52)*100 -> 109.50101 | AK52: =AK43+AK51 -> 27712372 | AL52: =(AK52/AI52)*100 -> 108.68931
B53: ='Balanço Contab'!B51 -> Total do Capital Próprio e do Passivo | D53: =D36+D52 -> 43877152 | E53: =E36+E52 -> 47937627 | F53: =F36+F52 -> 52072172 | G53: =E53-D53 -> 4060475 | H53: =F53-E53 -> 4134545 | K53: =B53 -> Total do Capital Próprio e do Passivo | M53: =M36+M52 -> 43877152 | N53: =M53/$M$53 -> 1 | O53: =O36+O52 -> 47937627 | P53: =O53/$O$53 -> 1 | Q53: =Q36+Q52 -> 52072172 | R53: =Q53/$Q$53 -> 1 | U53: =K53 -> Total do Capital Próprio e do Passivo | W53: =M53 -> 43877152 | X53: =(W53/W53)*100 -> 100 | Y53: =O53 -> 47937627 | Z53: =(Y53/W53)*100 -> 109.25419 | AA53: =Q53 -> 52072172 | AB53: =(AA53/W53)*100 -> 118.67719 | AE53: =U53 -> Total do Capital Próprio e do Passivo | AG53: =AG36+AG52 -> 43877152 | AH53: =(AG53/AG53)*100 -> 100 | AI53: =AI36+AI52 -> 47937627 | AJ53: =(AI53/AG53)*100 -> 109.25419 | AK53: =AK36+AK52 -> 52072172 | AL53: =(AK53/AI53)*100 -> 108.62484
D55: =D53-D24 -> 0 | E55: =E53-E24 -> 0 | F55: =F53-F24 -> 0 | G55: =G53-G24 -> 0 | H55: =H53-H24 -> 0 | M55: =(M15+M23)-(M36+M43+M51) -> 0 | N55: =(N15+N23)-(N36+N43+N51) -> 0 | O55: =(O15+O23)-(O36+O43+O51) -> 0 | P55: =(P15+P23)-(P36+P43+P51) -> 0 | Q55: =(Q15+Q23)-(Q36+Q43+Q51) -> 0 | R55: =(R15+R23)-(R36+R43+R51) -> 0 | W55: =(W15+W23)-(W36+W43+W51) -> 0 | Y55: =(Y15+Y23)-(Y36+Y43+Y51) -> 0 | AA55: =(AA15+AA23)-(AA36+AA43+AA51) -> 0 | AG55: =(AG15+AG23)-(AG36+AG43+AG51) -> 0 | AI55: =(AI15+AI23)-(AI36+AI43+AI51) -> 0 | AK55: =(AK15+AK23)-(AK36+AK43+AK51) -> 0
B57: Demonstração dos resultados a 31 de dezembro | H57: Mapa de Mutação de Valores | K57: Demonstração dos resultados a 31 de dezembro | U57: Demonstração dos resultados a 31 de dezembro | AE57: Demonstração dos resultados a 31 de dezembro
B58: RENDIMENTOS E GASTOS | C58: Notas | D58: Anos | G58: Valores Absolutos (€) | K58: RENDIMENTOS E GASTOS | L58: Notas | M58: 2022 | O58: 2023 | Q58: 2024 | U58: RENDIMENTOS E GASTOS | V58: Notas | W58: 2022 | Y58: 2023 | AA58: 2024 | AE58: RENDIMENTOS E GASTOS | AF58: Notas | AG58: 2022 | AI58: 2023 | AK58: 2024
D59: 2022 | E59: 2023 | F59: 2024 | G59: (2023-2022) | H59: (2024)-(2023) | M59: Valor (€) | N59: % | O59: Valor (€) | P59: % | Q59: Valor (€) | R59: % | W59: Valor (€) | X59: IBF | Y59: Valor (€) | Z59: IBF | AA59: Valor (€) | AB59: IBF | AG59: Valor (€) | AH59: IBM | AI59: Valor (€) | AJ59: IBM | AK59: Valor (€) | AL59: IBM
B60: ='DR Contab'!B7 -> Vendas e serviços prestados | D60: ='DR Contab'!D7 -> 34414527 | E60: ='DR Contab'!E7 -> 36103943 | F60: ='DR Contab'!F7 -> 39540477 | G60: =E60-D60 -> 1689416 | H60: =F60-E60 -> 3436534 | K60: =B60 -> Vendas e serviços prestados | M60: =D60 -> 34414527 | N60: =M60/$M$60 -> 1 | O60: =E60 -> 36103943 | P60: =O60/$O$60 -> 1 | Q60: =F60 -> 39540477 | R60: =Q60/$Q$60 -> 1 | U60: =K60 -> Vendas e serviços prestados | W60: =M60 -> 34414527 | X60: =(W60/W60)*100 -> 100 | Y60: =O60 -> 36103943 | Z60: =(Y60/W60)*100 -> 104.90902 | AA60: =Q60 -> 39540477 | AB60: =(AA60/W60)*100 -> 114.89473 | AE60: =U60 -> Vendas e serviços prestados | AG60: =W60 -> 34414527 | AH60: =(AG60/AG60)*100 -> 100 | AI60: =Y60 -> 36103943 | AJ60: =(AI60/AG60)*100 -> 104.90902 | AK60: =AA60 -> 39540477 | AL60: =(AK60/AI60)*100 -> 109.51845
B61: ='DR Contab'!B8 -> Subsídios à exploração | D61: ='DR Contab'!D8 -> 71600 | E61: ='DR Contab'!E8 -> 42589 | F61: ='DR Contab'!F8 -> 870 | G61: =E61-D61 -> -29011 | H61: =F61-E61 -> -41719 | K61: =B61 -> Subsídios à exploração | M61: =D61 -> 71600 | N61: =M61/$M$60 -> 0.0020805168 | O61: =E61 -> 42589 | P61: =O61/$O$60 -> 0.0011796218 | Q61: =F61 -> 870 | R61: =Q61/$Q$60 -> 2.2002769e-05 | U61: =K61 -> Subsídios à exploração | W61: =M61 -> 71600 | X61: =(W61/W61)*100 -> 100 | Y61: =O61 -> 42589 | Z61: =(Y61/W61)*100 -> 59.481844 | AA61: =Q61 -> 870 | AB61: =(AA61/W61)*100 -> 1.2150838 | AE61: =U61 -> Subsídios à exploração | AG61: =W61 -> 71600 | AH61: =(AG61/AG61)*100 -> 100 | AI61: =Y61 -> 42589 | AJ61: =(AI61/AG61)*100 -> 59.481844 | AK61: =AA61 -> 870 | AL61: =(AK61/AI61)*100 -> 2.042781
B62: ='DR Contab'!B9 -> Variação nos inventários da produção | D62: ='DR Contab'!D9 -> 3248 | E62: ='DR Contab'!E9 -> -59213 | F62: ='DR Contab'!F9 -> 131969 | G62: =E62-D62 -> -62461 | H62: =F62-E62 -> 191182 | K62: =B62 -> Variação nos inventários da produção | M62: =D62 -> 3248 | N62: =M62/$M$60 -> 9.4378749e-05 | O62: =E62 -> -59213 | P62: =O62/$O$60 -> -0.0016400702 | Q62: =F62 -> 131969 | R62: =Q62/$Q$60 -> 0.0033375672 | U62: =K62 -> Variação nos inventários da produção | W62: =M62 -> 3248 | X62: =(W62/W62)*100 -> 100 | Y62: =O62 -> -59213 | AA62: =Q62 -> 131969 | AB62: =(AA62/W62)*100 -> 4063.085 | AE62: =U62 -> Variação nos inventários da produção | AG62: =W62 -> 3248 | AH62: =(AG62/AG62)*100 -> 100 | AI62: =Y62 -> -59213 | AK62: =AA62 -> 131969
B63: ='DR Contab'!B10 -> Trabalhos para a própria entidade | D63: ='DR Contab'!D10 -> 0 | E63: ='DR Contab'!E10 -> 0 | F63: ='DR Contab'!F10 -> 0 | I63: O Mapa de Mutação de Valores tem como objetivo facilitar a análise dos aumentos e diminuições nos Rendimentos, Gastos e Resultados. Pelo que o sinal (+) mostra o aumento e o sinal (-) a redução. Assim, tendo em conta que os Gastos têm sinal (-) deve-se considerar a alteração da fórmula. Exceto naqueles em que os valores alternam entre positivos e negativos | K63: =B63 -> Trabalhos para a própria entidade | N63: =M63/$M$60 -> 0 | P63: =O63/$O$60 -> 0 | R63: =Q63/$Q$60 -> 0 | U63: =K63 -> Trabalhos para a própria entidade | AE63: =U63 -> Trabalhos para a própria entidade
B64: ='DR Contab'!B11 -> Custo das mercadorias vendidas e matérias consumidas | D64: ='DR Contab'!D11 -> -9270182 | E64: ='DR Contab'!E11 -> -9474096 | F64: ='DR Contab'!F11 -> -10429861 | G64: =(E64*(-1))-(D64*(-1)) -> 203914 | H64: =(F64*(-1))-(E64*(-1)) -> 955765 | I64: Aumento de gastos com MVMC | K64: =B64 -> Custo das mercadorias vendidas e matérias consumidas | M64: =D64 -> -9270182 | N64: =M64/$M$60 -> -0.26936828 | O64: =E64 -> -9474096 | P64: =O64/$O$60 -> -0.26241167 | Q64: =F64 -> -10429861 | R64: =Q64/$Q$60 -> -0.26377681 | U64: =K64 -> Custo das mercadorias vendidas e matérias consumidas | W64: =M64 -> -9270182 | X64: =(W64/W64)*100 -> 100 | Y64: =O64 -> -9474096 | Z64: =(Y64/W64)*100 -> 102.19968 | AA64: =Q64 -> -10429861 | AB64: =(AA64/W64)*100 -> 112.50978 | AE64: =U64 -> Custo das mercadorias vendidas e matérias consumidas | AG64: =W64 -> -9270182 | AH64: =(AG64/AG64)*100 -> 100 | AI64: =Y64 -> -9474096 | AJ64: =(AI64/AG64)*100 -> 102.19968 | AK64: =AA64 -> -10429861 | AL64: =(AK64/AI64)*100 -> 110.08819
B65: ='DR Contab'!B12 -> Fornecimentos e serviços externos | D65: ='DR Contab'!D12 -> -10472728 | E65: ='DR Contab'!E12 -> -10062717 | F65: ='DR Contab'!F12 -> -13103785 | G65: =(E65*(-1))-(D65*(-1)) -> -410011 | H65: =(F65*(-1))-(E65*(-1)) -> 3041068 | I65: Diminuição de gastos com FSE em 2023 e aumento em 2024 | K65: =B65 -> Fornecimentos e serviços externos | M65: =D65 -> -10472728 | N65: =M65/$M$60 -> -0.30431126 | O65: =E65 -> -10062717 | P65: =O65/$O$60 -> -0.27871518 | Q65: =F65 -> -13103785 | R65: =Q65/$Q$60 -> -0.33140179 | U65: =K65 -> Fornecimentos e serviços externos | W65: =M65 -> -10472728 | X65: =(W65/W65)*100 -> 100 | Y65: =O65 -> -10062717 | Z65: =(Y65/W65)*100 -> 96.084965 | AA65: =Q65 -> -13103785 | AB65: =(AA65/W65)*100 -> 125.12294 | AE65: =U65 -> Fornecimentos e serviços externos | AG65: =W65 -> -10472728 | AH65: =(AG65/AG65)*100 -> 100 | AI65: =Y65 -> -10062717 | AJ65: =(AI65/AG65)*100 -> 96.084965 | AK65: =AA65 -> -13103785 | AL65: =(AK65/AI65)*100 -> 130.22114
B66: ='DR Contab'!B13 -> Gastos com pessoal | D66: ='DR Contab'!D13 -> -8709967 | E66: ='DR Contab'!E13 -> -9570544 | F66: ='DR Contab'!F13 -> -10311572 | G66: =(E66*(-1))-(D66*(-1)) -> 860577 | H66: =(F66*(-1))-(E66*(-1)) -> 741028 | I66: Aumento de Gastos c/Pessoal | K66: =B66 -> Gastos com pessoal | M66: =D66 -> -8709967 | N66: =M66/$M$60 -> -0.25308984 | O66: =E66 -> -9570544 | P66: =O66/$O$60 -> -0.26508307 | Q66: =F66 -> -10311572 | R66: =Q66/$Q$60 -> -0.26078522 | U66: =K66 -> Gastos com pessoal | W66: =M66 -> -8709967 | X66: =(W66/W66)*100 -> 100 | Y66: =O66 -> -9570544 | Z66: =(Y66/W66)*100 -> 109.88037 | AA66: =Q66 -> -10311572 | AB66: =(AA66/W66)*100 -> 118.38819 | AE66: =U66 -> Gastos com pessoal | AG66: =W66 -> -8709967 | AH66: =(AG66/AG66)*100 -> 100 | AI66: =Y66 -> -9570544 | AJ66: =(AI66/AG66)*100 -> 109.88037 | AK66: =AA66 -> -10311572 | AL66: =(AK66/AI66)*100 -> 107.7428
B67: ='DR Contab'!B14 -> Imparidade de inventários (perdas/reversões) | D67: ='DR Contab'!D14 -> 24000 | E67: ='DR Contab'!E14 -> -7482 | F67: ='DR Contab'!F14 -> 7482 | G67: =E67-D67 -> -31482 | H67: =F67-E67 -> 14964 | K67: =B67 -> Imparidade de inventários (perdas/reversões) | M67: =D67 -> 24000 | N67: =M67/$M$60 -> 0.00069737992 | O67: =E67 -> -7482 | P67: =O67/$O$60 -> -0.00020723498 | Q67: =F67 -> 7482 | R67: =Q67/$Q$60 -> 0.00018922382 | U67: =K67 -> Imparidade de inventários (perdas/reversões) | W67: =M67 -> 24000 | X67: =(W67/W67)*100 -> 100 | Y67: =O67 -> -7482 | AA67: =Q67 -> 7482 | AB67: =(AA67/W67)*100 -> 31.175 | AE67: =U67 -> Imparidade de inventários (perdas/reversões) | AG67: =W67 -> 24000 | AH67: =(AG67/AG67)*100 -> 100 | AI67: =Y67 -> -7482 | AK67: =AA67 -> 7482
B68: ='DR Contab'!B15 -> Imparidade de dívidas a receber (perdas/reversões) | D68: ='DR Contab'!D15 -> -1074082 | E68: ='DR Contab'!E15 -> -530467 | F68: ='DR Contab'!F15 -> -403235 | G68: =(E68*(-1))-(D68*(-1)) -> -543615 | H68: =(F68*(-1))-(E68*(-1)) -> -127232 | I68: Diminuição de perdas por imparidade | K68: =B68 -> Imparidade de dívidas a receber (perdas/reversões) | M68: =D68 -> -1074082 | N68: =M68/$M$60 -> -0.031210134 | O68: =E68 -> -530467 | P68: =O68/$O$60 -> -0.014692772 | Q68: =F68 -> -403235 | R68: =Q68/$Q$60 -> -0.010198031 | U68: =K68 -> Imparidade de dívidas a receber (perdas/reversões) | W68: =M68 -> -1074082 | X68: =(W68/W68)*100 -> 100 | Y68: =O68 -> -530467 | Z68: =(Y68/W68)*100 -> 49.387942 | AA68: =Q68 -> -403235 | AB68: =(AA68/W68)*100 -> 37.542292 | AE68: =U68 -> Imparidade de dívidas a receber (perdas/reversões) | AG68: =W68 -> -1074082 | AH68: =(AG68/AG68)*100 -> 100 | AI68: =Y68 -> -530467 | AJ68: =(AI68/AG68)*100 -> 49.387942 | AK68: =AA68 -> -403235 | AL68: =(AK68/AI68)*100 -> 76.015096
B69: ='DR Contab'!B16 -> Aumentos/reduções de justo valor | D69: ='DR Contab'!D16 -> -211 | E69: ='DR Contab'!E16 -> 91 | F69: ='DR Contab'!F16 -> -58 | G69: =E69-D69 -> 302 | H69: =F69-E69 -> -149 | K69: =B69 -> Aumentos/reduções de justo valor | M69: =D69 -> -211 | N69: =M69/$M$60 -> -6.1311318e-06 | O69: =E69 -> 91 | P69: =O69/$O$60 -> 2.5205003e-06 | Q69: =F69 -> -58 | R69: =Q69/$Q$60 -> -1.4668513e-06 | U69: =K69 -> Aumentos/reduções de justo valor | W69: =M69 -> -211 | X69: =(W69/W69)*100 -> 100 | Y69: =O69 -> 91 | AA69: =Q69 -> -58 | AB69: =(AA69/W69)*100 -> 27.488152 | AE69: =U69 -> Aumentos/reduções de justo valor | AG69: =W69 -> -211 | AH69: =(AG69/AG69)*100 -> 100 | AI69: =Y69 -> 91 | AK69: =AA69 -> -58
B70: ='DR Contab'!B17 -> Ganhos/Perdas em empresas do grupo | D70: ='DR Contab'!D17 -> 0 | E70: ='DR Contab'!E17 -> 0 | F70: ='DR Contab'!F17 -> 0 | G70: =E70-D70 -> 0 | H70: =F70-E70 -> 0 | K70: =B70 -> Ganhos/Perdas em empresas do grupo | M70: =D70 -> 0 | N70: =M70/$M$60 -> 0 | O70: =E70 -> 0 | P70: =O70/$O$60 -> 0 | Q70: =F70 -> 0 | R70: =Q70/$Q$60 -> 0 | U70: =K70 -> Ganhos/Perdas em empresas do grupo | W70: =M70 -> 0 | Y70: =O70 -> 0 | AA70: =Q70 -> 0 | AE70: =U70 -> Ganhos/Perdas em empresas do grupo | AG70: =W70 -> 0 | AI70: =Y70 -> 0 | AK70: =AA70 -> 0
B71: ='DR Contab'!B18 -> Outros rendimentos e ganhos | D71: ='DR Contab'!D18 -> 1262832 | E71: ='DR Contab'!E18 -> 768393 | F71: ='DR Contab'!F18 -> 677442 | G71: =E71-D71 -> -494439 | H71: =F71-E71 -> -90951 | K71: =B71 -> Outros rendimentos e ganhos | M71: =D71 -> 1262832 | N71: =M71/$M$60 -> 0.036694736 | O71: =E71 -> 768393 | P71: =O71/$O$60 -> 0.0212828 | Q71: =F71 -> 677442 | R71: =Q71/$Q$60 -> 0.017132874 | U71: =K71 -> Outros rendimentos e ganhos | W71: =M71 -> 1262832 | X71: =(W71/W71)*100 -> 100 | Y71: =O71 -> 768393 | Z71: =(Y71/W71)*100 -> 60.846811 | AA71: =Q71 -> 677442 | AB71: =(AA71/W71)*100 -> 53.644665 | AE71: =U71 -> Outros rendimentos e ganhos | AG71: =W71 -> 1262832 | AH71: =(AG71/AG71)*100 -> 100 | AI71: =Y71 -> 768393 | AJ71: =(AI71/AG71)*100 -> 60.846811 | AK71: =AA71 -> 677442 | AL71: =(AK71/AI71)*100 -> 88.163479
B72: ='DR Contab'!B19 -> Outros gastos e perdas | D72: ='DR Contab'!D19 -> -230470 | E72: ='DR Contab'!E19 -> -285783 | F72: ='DR Contab'!F19 -> -346147 | G72: =(E72*(-1))-(D72*(-1)) -> 55313 | H72: =(F72*(-1))-(E72*(-1)) -> 60364 | I72: Aumento de outros gastos em 2023 e diminuição de gastos em 2024 | K72: =B72 -> Outros gastos e perdas | M72: =D72 -> -230470 | N72: =M72/$M$60 -> -0.0066968812 | O72: =E72 -> -285783 | P72: =O72/$O$60 -> -0.007915562 | Q72: =F72 -> -346147 | R72: =Q72/$Q$60 -> -0.0087542444 | U72: =K72 -> Outros gastos e perdas | W72: =M72 -> -230470 | X72: =(W72/W72)*100 -> 100 | Y72: =O72 -> -285783 | Z72: =(Y72/W72)*100 -> 124.00009 | AA72: =Q72 -> -346147 | AB72: =(AA72/W72)*100 -> 150.19178 | AE72: =U72 -> Outros gastos e perdas | AG72: =W72 -> -230470 | AH72: =(AG72/AG72)*100 -> 100 | AI72: =Y72 -> -285783 | AJ72: =(AI72/AG72)*100 -> 124.00009 | AK72: =AA72 -> -346147 | AL72: =(AK72/AI72)*100 -> 121.12232
B73: ='DR Contab'!B20 -> Resultado antes de depreciações, gastos de financiamento e impostos | D73: =SUM(D60:D72) -> 6018567 | E73: =SUM(E60:E72) -> 6924714 | F73: =SUM(F60:F72) -> 5763582 | G73: =E73-D73 -> 906147 | H73: =F73-E73 -> -1161132 | K73: =B73 -> Resultado antes de depreciações, gastos de financiamento e impostos | M73: =SUM(M60:M72) -> 6018567 | N73: =M73/$M$60 -> 0.17488449 | O73: =SUM(O60:O72) -> 6924714 | P73: =O73/$O$60 -> 0.19179938 | Q73: =SUM(Q60:Q72) -> 5763582 | R73: =Q73/$Q$60 -> 0.1457641 | U73: =K73 -> Resultado antes de depreciações, gastos de financiamento e impostos | W73: =M73 -> 6018567 | X73: =(W73/W73)*100 -> 100 | Y73: =O73 -> 6924714 | Z73: =(Y73/W73)*100 -> 115.05586 | AA73: =Q73 -> 5763582 | AB73: =(AA73/W73)*100 -> 95.76336 | AE73: =U73 -> Resultado antes de depreciações, gastos de financiamento e impostos | AG73: =W73 -> 6018567 | AH73: =(AG73/AG73)*100 -> 100 | AI73: =Y73 -> 6924714 | AJ73: =(AI73/AG73)*100 -> 115.05586 | AK73: =AA73 -> 5763582 | AL73: =(AK73/AI73)*100 -> 83.232058
B74: ='DR Contab'!B21 -> Gastos/reversões de depreciação e de amortização | D74: ='DR Contab'!D21 -> -3102483 | E74: ='DR Contab'!E21 -> -2957566 | F74: ='DR Contab'!F21 -> -2761538 | G74: =(E74*(-1))-(D74*(-1)) -> -144917 | H74: =(F74*(-1))-(E74*(-1)) -> -196028 | I74: Diminuição de gastos com Depreciações | K74: =B74 -> Gastos/reversões de depreciação e de amortização | M74: =D74 -> -3102483 | N74: =M74/$M$60 -> -0.090150389 | O74: =E74 -> -2957566 | P74: =O74/$O$60 -> -0.081918089 | Q74: =F74 -> -2761538 | R74: =Q74/$Q$60 -> -0.069840786 | U74: =K74 -> Gastos/reversões de depreciação e de amortização | W74: =M74 -> -3102483 | X74: =(W74/W74)*100 -> 100 | Y74: =O74 -> -2957566 | Z74: =(Y74/W74)*100 -> 95.328999 | AA74: =Q74 -> -2761538 | AB74: =(AA74/W74)*100 -> 89.010576 | AE74: =U74 -> Gastos/reversões de depreciação e de amortização | AG74: =W74 -> -3102483 | AH74: =(AG74/AG74)*100 -> 100 | AI74: =Y74 -> -2957566 | AJ74: =(AI74/AG74)*100 -> 95.328999 | AK74: =AA74 -> -2761538 | AL74: =(AK74/AI74)*100 -> 93.371982
B75: ='DR Contab'!B22 -> Imparidade de investimentos depreciáveis/amortizáveis (perdas/reversões) | D75: ='DR Contab'!D22 -> 0 | E75: ='DR Contab'!E22 -> 0 | F75: ='DR Contab'!F22 -> 0 | G75: =E75-D75 -> 0 | H75: =F75-E75 -> 0 | K75: =B75 -> Imparidade de investimentos depreciáveis/amortizáveis (perdas/reversões) | M75: =D75 -> 0 | N75: =M75/$M$60 -> 0 | O75: =E75 -> 0 | P75: =O75/$O$60 -> 0 | Q75: =F75 -> 0 | R75: =Q75/$Q$60 -> 0 | U75: =K75 -> Imparidade de investimentos depreciáveis/amortizáveis (perdas/reversões) | W75: =M75 -> 0 | Y75: =O75 -> 0 | AA75: =Q75 -> 0 | AE75: =U75 -> Imparidade de investimentos depreciáveis/amortizáveis (perdas/reversões) | AG75: =W75 -> 0 | AI75: =Y75 -> 0 | AK75: =AA75 -> 0
B76: ='DR Contab'!B23 -> Resultado Operacional (antes de gastos de financiamento e impostos) | D76: =SUM(D73:D75) -> 2916084 | E76: =SUM(E73:E75) -> 3967148 | F76: =SUM(F73:F75) -> 3002044 | G76: =E76-D76 -> 1051064 | H76: =F76-E76 -> -965104 | K76: =B76 -> Resultado Operacional (antes de gastos de financiamento e impostos) | M76: =SUM(M73:M75) -> 2916084 | N76: =M76/$M$60 -> 0.084734101 | O76: =SUM(O73:O75) -> 3967148 | P76: =O76/$O$60 -> 0.10988129 | Q76: =SUM(Q73:Q75) -> 3002044 | R76: =Q76/$Q$60 -> 0.075923313 | U76: =K76 -> Resultado Operacional (antes de gastos de financiamento e impostos) | W76: =M76 -> 2916084 | X76: =(W76/W76)*100 -> 100 | Y76: =O76 -> 3967148 | Z76: =(Y76/W76)*100 -> 136.04368 | AA76: =Q76 -> 3002044 | AB76: =(AA76/W76)*100 -> 102.94779 | AE76: =U76 -> Resultado Operacional (antes de gastos de financiamento e impostos) | AG76: =W76 -> 2916084 | AH76: =(AG76/AG76)*100 -> 100 | AI76: =Y76 -> 3967148 | AJ76: =(AI76/AG76)*100 -> 136.04368 | AK76: =AA76 -> 3002044 | AL76: =(AK76/AI76)*100 -> 75.672599
B77: ='DR Contab'!B24 -> Juros e rendimentos similares obtidos | D77: ='DR Contab'!D24 -> 1595 | E77: ='DR Contab'!E24 -> 93572 | F77: ='DR Contab'!F24 -> 47799 | G77: =E77-D77 -> 91977 | H77: =F77-E77 -> -45773 | K77: =B77 -> Juros e rendimentos similares obtidos | M77: =D77 -> 1595 | N77: =M77/$M$60 -> 4.6346707e-05 | O77: =E77 -> 93572 | P77: =O77/$O$60 -> 0.0025917391 | Q77: =F77 -> 47799 | R77: =Q77/$Q$60 -> 0.0012088625 | U77: =K77 -> Juros e rendimentos similares obtidos | W77: =M77 -> 1595 | X77: =(W77/W77)*100 -> 100 | Y77: =O77 -> 93572 | Z77: =(Y77/W77)*100 -> 5866.5831 | AA77: =Q77 -> 47799 | AB77: =(AA77/W77)*100 -> 2996.8025 | AE77: =U77 -> Juros e rendimentos similares obtidos | AG77: =W77 -> 1595 | AH77: =(AG77/AG77)*100 -> 100 | AI77: =Y77 -> 93572 | AJ77: =(AI77/AG77)*100 -> 5866.5831 | AK77: =AA77 -> 47799 | AL77: =(AK77/AI77)*100 -> 51.082589
B78: ='DR Contab'!B25 -> Juros de empresas do grupo | G78: =(E78*(-1))-(D78*(-1)) -> 0 | H78: =(F78*(-1))-(E78*(-1)) -> 0 | K78: =B78 -> Juros de empresas do grupo | M78: =D78 -> 0 | N78: =M78/$M$60 -> 0 | O78: =E78 -> 0 | P78: =O78/$O$60 -> 0 | Q78: =F78 -> 0 | R78: =Q78/$Q$60 -> 0 | U78: =K78 -> Juros de empresas do grupo | W78: =M78 -> 0 | Y78: =O78 -> 0 | AA78: =Q78 -> 0 | AE78: =U78 -> Juros de empresas do grupo | AG78: =W78 -> 0 | AI78: =Y78 -> 0 | AK78: =AA78 -> 0
B79: ='DR Contab'!B26 -> Juros e gastos similares suportados | D79: ='DR Contab'!D26 -> -635383 | E79: ='DR Contab'!E26 -> -972006 | F79: ='DR Contab'!F26 -> -1151303 | G79: =(E79*(-1))-(D79*(-1)) -> 336623 | H79: =(F79*(-1))-(E79*(-1)) -> 179297 | I79: Aumento de juros suportados | K79: =B79 -> Juros e gastos similares suportados | M79: =D79 -> -635383 | N79: =M79/$M$60 -> -0.018462639 | O79: =E79 -> -972006 | P79: =O79/$O$60 -> -0.026922433 | Q79: =F79 -> -1151303 | R79: =Q79/$Q$60 -> -0.029117074 | U79: =K79 -> Juros e gastos similares suportados | W79: =M79 -> -635383 | X79: =(W79/W79)*100 -> 100 | Y79: =O79 -> -972006 | Z79: =(Y79/W79)*100 -> 152.97954 | AA79: =Q79 -> -1151303 | AB79: =(AA79/W79)*100 -> 181.19827 | AE79: =U79 -> Juros e gastos similares suportados | AG79: =W79 -> -635383 | AH79: =(AG79/AG79)*100 -> 100 | AI79: =Y79 -> -972006 | AJ79: =(AI79/AG79)*100 -> 152.97954 | AK79: =AA79 -> -1151303 | AL79: =(AK79/AI79)*100 -> 118.44608
B80: ='DR Contab'!B27 -> Resultado antes de impostos | D80: =SUM(D76:D79) -> 2282296 | E80: =SUM(E76:E79) -> 3088714 | F80: =SUM(F76:F79) -> 1898540 | G80: =E80-D80 -> 806418 | H80: =F80-E80 -> -1190174 | K80: =B80 -> Resultado antes de impostos | M80: =SUM(M76:M79) -> 2282296 | N80: =M80/$M$60 -> 0.066317808 | O80: =SUM(O76:O79) -> 3088714 | P80: =O80/$O$60 -> 0.0855506 | Q80: =SUM(Q76:Q79) -> 1898540 | R80: =Q80/$Q$60 -> 0.048015101 | U80: =K80 -> Resultado antes de impostos | W80: =M80 -> 2282296 | X80: =(W80/W80)*100 -> 100 | Y80: =O80 -> 3088714 | Z80: =(Y80/W80)*100 -> 135.33363 | AA80: =Q80 -> 1898540 | AB80: =(AA80/W80)*100 -> 83.185529 | AE80: =U80 -> Resultado antes de impostos | AG80: =W80 -> 2282296 | AH80: =(AG80/AG80)*100 -> 100 | AI80: =Y80 -> 3088714 | AJ80: =(AI80/AG80)*100 -> 135.33363 | AK80: =AA80 -> 1898540 | AL80: =(AK80/AI80)*100 -> 61.467005
B81: ='DR Contab'!B28 -> Imposto s/ rendimento do período | D81: ='DR Contab'!D28 -> 25835 | E81: ='DR Contab'!E28 -> -740818 | F81: ='DR Contab'!F28 -> 380710 | G81: =E81-D81 -> -766653 | H81: =F81-E81 -> 1121528 | I81: Aumento de impostos em 2023 e diminuição de impostos em 2024 | K81: =B81 -> Imposto s/ rendimento do período | M81: =D81 -> 25835 | N81: =M81/$M$60 -> 0.00075070042 | O81: =E81 -> -740818 | P81: =O81/$O$60 -> -0.020519033 | Q81: =F81 -> 380710 | R81: =Q81/$Q$60 -> 0.0096283613 | U81: =K81 -> Imposto s/ rendimento do período | W81: =M81 -> 25835 | X81: =(W81/W81)*100 -> 100 | Y81: =O81 -> -740818 | AA81: =Q81 -> 380710 | AB81: =(AA81/W81)*100 -> 1473.6211 | AE81: =U81 -> Imposto s/ rendimento do período | AG81: =W81 -> 25835 | AH81: =(AG81/AG81)*100 -> 100 | AI81: =Y81 -> -740818 | AK81: =AA81 -> 380710
B82: ='DR Contab'!B29 -> Imposto diferido | D82: ='DR Contab'!D29 -> 0 | E82: ='DR Contab'!E29 -> 0 | F82: ='DR Contab'!F29 -> 0 | G82: =E82-D82 -> 0 | H82: =F82-E82 -> 0 | K82: =B82 -> Imposto diferido | M82: =D82 -> 0 | N82: =M82/$M$60 -> 0 | O82: =E82 -> 0 | P82: =O82/$O$60 -> 0 | Q82: =F82 -> 0 | R82: =Q82/$Q$60 -> 0 | U82: =K82 -> Imposto diferido | W82: =M82 -> 0 | Y82: =O82 -> 0 | AA82: =Q82 -> 0 | AE82: =U82 -> Imposto diferido | AG82: =W82 -> 0 | AI82: =Y82 -> 0 | AK82: =AA82 -> 0
B83: ='DR Contab'!B30 -> Resultado liquido do período | D83: =SUM(D80:D82) -> 2308131 | E83: =SUM(E80:E82) -> 2347896 | F83: =SUM(F80:F82) -> 2279250 | G83: =E83-D83 -> 39765 | H83: =F83-E83 -> -68646 | K83: =B83 -> Resultado liquido do período | M83: =SUM(M80:M82) -> 2308131 | N83: =M83/$M$60 -> 0.067068509 | O83: =SUM(O80:O82) -> 2347896 | P83: =O83/$O$60 -> 0.065031567 | Q83: =SUM(Q80:Q82) -> 2279250 | R83: =Q83/$Q$60 -> 0.057643462 | U83: =K83 -> Resultado liquido do período | W83: =M83 -> 2308131 | X83: =(W83/W83)*100 -> 100 | Y83: =O83 -> 2347896 | Z83: =(Y83/W83)*100 -> 101.72282 | AA83: =Q83 -> 2279250 | AB83: =(AA83/W83)*100 -> 98.748728 | AE83: =U83 -> Resultado liquido do período | AG83: =W83 -> 2308131 | AH83: =(AG83/AG83)*100 -> 100 | AI83: =Y83 -> 2347896 | AJ83: =(AI83/AG83)*100 -> 101.72282 | AK83: =AA83 -> 2279250 | AL83: =(AK83/AG83)*100 -> 98.748728
D85: =D83-D35 -> 0 | E85: =E83-E35 -> 0 | F85: =F83-F35 -> 0 | I85: Ajuste da fórmula de cálculo de variação de valores | M85: =M83-M35 -> 0 | O85: =O83-O35 -> 0 | Q85: =Q83-Q35 -> 0 | W85: =W83-W35 -> 0 | Y85: =Y83-Y35 -> 0 | AA85: =AA83-AA35 -> 0 | AG85: =AG83-AG35 -> 0 | AI85: =AI83-AI35 -> 0 | AK85: =AK83-AK35 -> 0
AC86: Casos em que o índice não representa a realidade que se pretende avaliar | AM86: Casos em que o índice não representa a realidade que se pretende avaliar

Sheet Folha1

Sheet Equilibrío Financeiro
B2: Quadro E.2: Síntese dos valores do balanço funcional e cálculos auxiliares | G2: (em euros)
B3: Rubricas | C3: Notas | D3: Anos
D4: 2021 (I) | E4: 2022 | F4: 2023 | G4: 2024
B5: AFL | D5: =+'Balanço Funcional'!D15 -> 25364486 | E5: =+'Balanço Funcional'!E15 -> 23534911 | F5: =+'Balanço Funcional'!F15 -> 22056780 | G5: =+'Balanço Funcional'!G15 -> 24537744
B6: AFL Exploração | D6: =+'Balanço Funcional'!D8+'Balanço Funcional'!D10 -> 21630561 | E6: =+'Balanço Funcional'!E8+'Balanço Funcional'!E10 -> 19738010 | F6: =+'Balanço Funcional'!F8+'Balanço Funcional'!F10 -> 18927612 | G6: =+'Balanço Funcional'!G8+'Balanço Funcional'!G10 -> 20972234 | H6: AFT + Inangíveis
B7: AFL Exploração média do período | D7: ----- | E7: =(E6+D6)/2 -> 20684286 | F7: =(F6+E6)/2 -> 19332811 | G7: =(G6+F6)/2 -> 19949924
B8: Inventários | D8: =+'Balanço Funcional'!D17 -> 2142568 | E8: =+'Balanço Funcional'!E17 -> 2476629 | F8: =+'Balanço Funcional'!F17 -> 2368546 | G8: =+'Balanço Funcional'!G17 -> 2667287
B9: Inventários média do período | D9: ----- | E9: =(D8+E8)/2 -> 2309598.5 | F9: =(E8+F8)/2 -> 2422587.5 | G9: =(F8+G8)/2 -> 2517916.5
B10: Matérias primas e mercadorias | D10: 2031389 | E10: 2362202 | F10: 2313333 | G10: 2480109 | H10: Ver se os subprodutos entram ou não/mercadorias
B11: Matérias primas e mercadorias média do período | D11: ----- | E11: =(D10+E10)/2 -> 2196795.5 | F11: =(E10+F10)/2 -> 2337767.5 | G11: =(F10+G10)/2 -> 2396721
B12: Clientes | D12: =+'Balanço Funcional'!D18 -> 9505101 | E12: =+'Balanço Funcional'!E18 -> 10993343 | F12: =+'Balanço Funcional'!F18 -> 13433628 | G12: =+'Balanço Funcional'!G18 -> 15033498
B13: Adiantamentos de clientes | D13: =+'Balanço Funcional'!D48 -> 288801 | E13: =+'Balanço Funcional'!E48 -> 174400 | F13: =+'Balanço Funcional'!F48 -> 1889441 | G13: =+'Balanço Funcional'!G48 -> 1863058
B14: (Clientes - Adiantamentos de clientes) média do período | D14: ----- | E14: =((D12-D13)+(E12-E13))/2 -> 10017622 | F14: =((E12-E13)+(F12-F13))/2 -> 11181565 | G14: =((F12-F13)+(G12-G13))/2 -> 12357314
B15: Meios financeiros líquidos (MFL) | D15: =+'Balanço Funcional'!D26 -> 1461954 | E15: =+'Balanço Funcional'!E26 -> 2257927 | F15: =+'Balanço Funcional'!F26 -> 4138413 | G15: =+'Balanço Funcional'!G26 -> 1799870 | H15: Caixa e DO
B16: Ativo corrente (NC+TA) | D16: =+'Balanço Funcional'!D22+'Balanço Funcional'!D27 -> 17121043 | E16: =+'Balanço Funcional'!E22+'Balanço Funcional'!E27 -> 20342241 | F16: =+'Balanço Funcional'!F22+'Balanço Funcional'!F27 -> 25880846 | G16: =+'Balanço Funcional'!G22+'Balanço Funcional'!G27 -> 27534428
B17: Ativo corrente média do período | D17: ----- | E17: =(E16+D16)/2 -> 18731642 | F17: =(F16+E16)/2 -> 23111544 | G17: =(G16+F16)/2 -> 26707637
B18: Total do ativo | D18: =+'Balanço Funcional'!D28 -> 42485529 | E18: =+'Balanço Funcional'!E28 -> 43877152 | F18: =+'Balanço Funcional'!F28 -> 47937627 | G18: =+'Balanço Funcional'!G28 -> 52072172
B19: Total do ativo média do período | D19: ----- | E19: =(D18+E18)/2 -> 43181340 | F19: =(E18+F18)/2 -> 45907390 | G19: =(F18+G18)/2 -> 50004900
B21: Capital próprio | D21: =+'Balanço Funcional'!D38 -> 18946407 | E21: =+'Balanço Funcional'!E38 -> 20592555 | F21: =+'Balanço Funcional'!F38 -> 22440758 | G21: =+'Balanço Funcional'!G38 -> 24359800
B22: Capital próprio média do período | D22: ----- | E22: =(D21+E21)/2 -> 19769481 | F22: =(E21+F21)/2 -> 21516656 | G22: =(F21+G21)/2 -> 23400279
B23: Capital próprio excluindo o RLP (N) | D23: ='Balanço Funcional'!D38-('Balanço Funcional'!D37) -> 19408653 | E23: ='Balanço Funcional'!E38-'Balanço Funcional'!E37 -> 18284424 | F23: =+'Balanço Funcional'!F38-'Balanço Funcional'!F37 -> 20092862 | G23: ='Balanço Funcional'!G38-'Balanço Funcional'!G37 -> 22080550
B24: Capital Próprio excluindo o RLP (N) média do período | C24: (II) | D24: ----- | E24: =(E23+D23)/2 -> 18846538 | F24: =(F23+E23)/2 -> 19188643 | G24: =(G23+F23)/2 -> 21086706 | H24: ver se é o de sem com o RLP ou sem o rLP
B25: Passivo não corrente | D25: =+'Balanço Funcional'!D44 -> 14554730 | E25: =+'Balanço Funcional'!E44 -> 14383300 | F25: =+'Balanço Funcional'!F44 -> 12835058 | G25: =+'Balanço Funcional'!G44 -> 15750541
B26: Recursos estáveis | D26: =+'Balanço Funcional'!D45 -> 33501137 | E26: =+'Balanço Funcional'!E45 -> 34975855 | F26: =+'Balanço Funcional'!F45 -> 35275816 | G26: =+'Balanço Funcional'!G45 -> 40110341
B27: Fornecedores | D27: =+'Balanço Funcional'!D47 -> 710998 | E27: =+'Balanço Funcional'!E47 -> 1415895 | F27: =+'Balanço Funcional'!F47 -> 633029 | G27: =+'Balanço Funcional'!G47 -> 721181
B28: Adiantamentos a fornecedores | D28: 219243 | E28: =+'Balanço Contab'!D71 -> 159197 | F28: =+'Balanço Contab'!E71 -> 154858 | G28: =+'Balanço Contab'!F71 -> 387998 | H28: Nota 13 do Anexo
B29: (Fornec. - Adiantamentos a fornec.) média do período | D29: ----- | E29: =((D27-D28)+(E27-E28))/2 -> 874226.5 | F29: =((E27-E28)+(F27-F28))/2 -> 867434.5 | G29: =((F27-F28)+(G27-G28))/2 -> 405677
B30: Passivo corrente (RC+TP) | D30: =+'Balanço Funcional'!D52+'Balanço Funcional'!D56 -> 9059375 | E30: ='Balanço Funcional'!E52+'Balanço Funcional'!E56 -> 8901297 | F30: =+'Balanço Funcional'!F52+'Balanço Funcional'!F56 -> 12661811 | G30: =+'Balanço Funcional'!G52+'Balanço Funcional'!G56 -> 11961831
B31: Total Cap. próprio + Passivo | D31: =+'Balanço Funcional'!D58 -> 42560512 | E31: =+'Balanço Funcional'!E58 -> 43877152 | F31: =+'Balanço Funcional'!F58 -> 47937627 | G31: =+'Balanço Funcional'!G58 -> 52072172
B32: (Total do Cap. próprio + Passivo) média do período | D32: ----- | E32: =(D31+E31)/2 -> 43218832 | F32: =(E31+F31)/2 -> 45907390 | G32: =(F31+G31)/2 -> 50004900
B34: Notas:
B35: (I) A consideração do ano 2021 tem como objetivo calcular os valores da média do período para os anos 2022, 2023, 2024.
B36: (II) No cálculo do valor do Capital Próprio excluindo o RLP (N) média do período apenas é retirado o RLP do ano em questão (ano (N)).
B38: Quadro E.3: Síntese dos valores da demostração dos resultados e cálculos auxiliares | G38: (em euros)
B39: Rubricas | C39: Notas | D39: Anos
D40: 2021 (III) | E40: 2022 | F40: 2023 | G40: 2024
B41: Volume de negócios | C41: (IV) | D41: ---- | E41: =+'DR Contab'!D7 -> 34414527 | F41: =+'DR Contab'!E7 -> 36103943 | G41: =+'DR Contab'!F7 -> 39540477
B42: Volume de negócios com IVA | C42: (V) | D42: ---- | E42: =E61*1.23+E62 -> 40430186 | F42: =F61*1.23+F62 -> 41916678 | G42: =G61*1.23+G62 -> 45724608 | H42: VN com IVA = VN mercado interno x 1,23 +VN mercado externo
B43: CMVMC | D43: ---- | E43: =-'DR Contab'!D11 -> 9270182 | F43: =-'DR Contab'!E11 -> 9474096 | G43: =-'DR Contab'!F11 -> 10429861 | H43: DR | I43: ver se é menosl ou masi
B44: Compras | D44: ---- | E44: 9537531 | F44: 9425227 | G44: 10596637 | H44: Nota 28 Anexo
B45: Compras com IVA | C45: (V) | D45: ---- | E45: =E70*1.23+E73 -> 10853710 | F45: =F70*1.23+F73 -> 10769264 | G45: =G70*1.23+G73 -> 12010228 | H45: Compras com IVA = Compras mercado interno x 1,23 + Compras mercado externo
B46: FSE adquiridos a crédito (trabalhos especializados) | C46: (VI) | D46: ---- | H46: Taxas no quadro E.7 e FSE a crédito no E.6
B47: FSE adquiridos a crédito (trabalhos especializados) com IVA | C47: (V) | D47: ---- | H47: FSE com IVA = FSE mercado interno x 1,23 x FSE mercado externo
B48: Resultado operacional (EBIT) | D48: ---- | E48: =+'DR Contab'!D23 -> 2916084 | F48: =+'DR Contab'!E23 -> 3967148 | G48: =+'DR Contab'!F23 -> 3002044 | H48: DR
B49: Rendimentos financeiros | D49: ---- | E49: =+'DR Contab'!D24 -> 1595 | F49: =+'DR Contab'!E24 -> 93572 | G49: =+'DR Contab'!F24 -> 47799 | H49: Juros e rendimentos similares obtidos (DR)
B50: Gastos financeiros | D50: ---- | E50: =-('DR Contab'!D25+'DR Contab'!D26) -> 635383 | F50: =-('DR Contab'!E26) -> 972006 | G50: =-('DR Contab'!F26) -> 1151303 | H50: Juros e gastos similares suportados e juros das empresas do grupo (DR)
B52: Notas:
B53: (III) Nestas rubricas não é necessário considerar os valores de 2021, já que não se calculam valores da média do período neste quadro.
B54: (IV) Volume de Negócios = vendas + serviços prestados
B55: (V) Considerar apenas o IVA no VN, Compras e FSE do mercado interno. As taxas de IVA são as que constam do quadro E.7.
B56: (VI) De acordo com o Anexo da Bial, nota 14: Fornecedores correntes – corresponde, maioritariamente, a fornecedores de matérias-primas e prestadores de serviços de I&D - que são os serviços especializados no detalhe de FSE (nota 21).
B58: Quadro E.4: Informação da nota 25 do Anexo e informação adicional - Volume de negócios por mercado | G58: (em euros)
B59: Rubricas | C59: Notas | D59: Anos
D60: 2021 (III) | E60: 2022 | F60: 2023 | G60: 2024
B61: Mercado interno | D61: ---- | E61: 26155041 | F61: 25272760 | G61: 26887524
B62: Mercado externo | D62: ---- | E62: 8259486 | F62: 10831183 | G62: 12652953
B63: Total VN | D63: ---- | E63: =E61+E62 -> 34414527 | F63: =F61+F62 -> 36103943 | G63: =G61+G62 -> 39540477
B66: Quadro E.5: Pressupostos relativos às compras e FSE----ENUNCIADO-Compras e FSE por mercados | G66: (em euros)
B67: Rubricas | C67: Notas | D67: Anos
D68: 2021 (III) | E68: 2022 | F68: 2023 | G68: 2024
B69: Mercado interno | D69: ---- | E69: =E70+E71 -> 16195247 | F69: =F70+F71 -> 15906358 | G69: =G70+G71 -> 19249834
B70: Compras | C70: (VII) | D70: ---- | E70: 5722519 | F70: 5843641 | G70: 6146049
B71: FSE | C71: (VIII) | D71: ---- | E71: 10472728 | F71: 10062717 | G71: 13103785
B72: Mercado externo | D72: ---- | E72: =E73+E74 -> 3815012 | F72: =F73+F74 -> 3581586 | G72: =G73+G74 -> 4450588
B73: Compras | C73: (VII) | D73: ---- | E73: 3815012 | F73: 3581586 | G73: 4450588
B74: FSE | C74: (VIII) | D74: ---- | E74: 0 | F74: 0 | G74: 0
B75: Total de compras e FSE | D75: ---- | E75: =E69+E72 -> 20010259 | F75: =F69+F72 -> 19487944 | G75: =G69+G72 -> 23700422
B77: (VII) Compras: respeita à aquisição de mat. primas, sub. e mercadorias
B78: (VIII) FSE: nem todos os FSE são comprados a crédito. Logo, a seguir detalham-se os valores, por mercado, dos FSE adquiridos a crédito
B80: Quadro E.6: Detalhe, por mercados, dos FSE que são adquiridos a crédito
D81: 2022 | E81: 2023 | F81: 2024
B82: Mercado interno
B83: Mercado externo
B87: Quadro E.7: Taxas de IVA aplicadas às vendas, serviços prestados, compras e FSE----ENUNCIADO
B88: Rubricas | C88: Notas | D88: Anos
D89: 2021 (III) | E89: 2022 | F89: 2023 | G89: 2024
B90: Volume de negócios (vendas e serviços prest.) | D90: ---- | E90: 0.23 | F90: 0.23 | G90: 0.23
B91: Compras | D91: ---- | E91: 0.23 | F91: 0.23 | G91: 0.23
B92: FSE (exceto água) | D92: ---- | E92: 0.23 | F92: 0.23 | G92: 0.23
B93: FSE (àgua) | D93: ---- | E93: 0.06 | F93: 0.06 | G93: 0.06
B96: Quadro E.8: Cálculo dos indicadores e rácios de equilíbrio financeiro de curto prazo e comparação com o setor
B97: Indicadores e rácios | C97: Notas | D97: Bial | H97: Fórmula | I97: Notas | J97: Valores do setor (ano / quartil)
D98: 2021 (IX) | E98: 2022 | F98: 2023 | G98: 2024 | J98: 2022 | L98: 2023 | N98: 2024
B99: Rotação de Inventários | C99: (X) | D99: ---- | E99: =E43/(D8+E8)*2 -> 4.0137634 | F99: =F43/(E8+F8)*2 -> 3.9107343 | G99: =G43/(F8+G8)*2 -> 4.1422585 | H99: CPV / (Inv.+A. biológicos) média do período | J99: =(1/J101)*365 -> 1.3321168 | L99: =(1/L101)*365 -> 1.2331081 | N99: =(1/N101)*365 -> 1.2414966
B100: Rotação de matérias primas e mercadorias | D100: ---- | E100: =(E43/(D10+E10))*2 -> 4.2198657 | F100: =(F43/(E10+F10))*2 -> 4.0526254 | G100: =(G43/(F10+G10))*2 -> 4.351721 | H100: CMVMC / (Mat. primas + Merc.) média do período
B101: DMI (Dias) | C101: (X) | D101: ---- | E101: =((D8+E8)/2/E43)*365 -> 90.937098 | F101: =((E8+F8)/2/F43)*365 -> 93.332856 | G101: =((F8+G8)/2/G43)*365 -> 88.116181 | H101: [(Inv.+A. biológicos) média do período /CPV]x365 | J101: 274 | K101: Q3 | L101: 296 | M101: Q3 | N101: 294 | O101: Q3
B102: DMMP&M (Dias) | D102: ---- | E102: =((D10+E10)/2/E43)*365 -> 86.495644 | F102: =((E10+F10)/2/F43)*365 -> 90.065072 | G102: =((F10+G10)/2/G43)*365 -> 83.874863 | H102: [(Mat. primas+Merc.) média do período /CMVMC]x365
B103: PMR (Dias) | D103: ---- | E103: =E14/E42*365 -> 90.438164 | F103: =F14/F42*365 -> 97.366283 | G103: =G14/G42*365 -> 98.643152 | H103: [[(Clientes - Adiant. de clientes) méd. do período]/(VN com IVA)]x365 | J103: 74 | K103: Q2 | L103: 77 | M103: Q2 | N103: 68 | O103: Q2
B104: PMP (Dias) | C104: (XI) | D104: ---- | E104: =(E29/(E45+E47))*365 -> 29.399409 | F104: =(F29/(F45+F47))*365 -> 29.399742 | G104: =(G29/(G45+G47))*365 -> 12.328834 | H104: [[(Fornec. - Adiant. a fornec.) méd. do período]/(Comp. com IVA+FSE com IVA)]x365 | J104: 106 | K104: Q3 | L104: 122 | M104: Q3 | N104: 114 | O104: Q3
B105: Rotação do ativo total | D105: ---- | E105: =E41/E19 -> 0.79697681 | F105: =F41/F19 -> 0.78645167 | G105: =G41/G19 -> 0.79073206 | H105: VN / Total do ativo média do período
B106: Rotação das AFL exploração | D106: ---- | E106: =E41/E7 -> 1.6638006 | F106: =F41/F7 -> 1.8674958 | G106: =G41/G7 -> 1.9819864 | H106: VN / AFL Expl. média do período
B107: Rotação do ativo corrente | D107: ---- | E107: =E41/E17 -> 1.8372403 | F107: =F41/F17 -> 1.5621606 | G107: =G41/G17 -> 1.4804933 | H107: VN / Ativo corrente média do período
B108: Rotação do capital próprio | D108: ---- | E108: =E41/E22 -> 1.7407906 | F108: =F41/F22 -> 1.6779532 | G108: =G41/G22 -> 1.6897438 | H108: VN / Capital próprio média do período
B109: Rotação do capital próprio excluindo o RLP (N) | D109: ---- | E109: =E41/E24 -> 1.8260397 | F109: =F41/F24 -> 1.8815266 | G109: =G41/G24 -> 1.8751377 | H109: VN / Capital Próprio excluindo o RLP (N) média do período
B110: DCO (Dias) | D110: ---- | E110: =+E101+E103 -> 181.37526 | F110: =+F101+F103 -> 190.69914 | G110: =+G101+G103 -> 186.75933 | H110: DMI + PMR | I110: (XII) | J110: =(J104+J111) -> 404 | L110: =L111+L104 -> 428 | N110: =N111+N104 -> 394
B111: DCF (Dias) | D111: ---- | E111: =+E110-E104 -> 151.97585 | F111: =+F110-F104 -> 161.2994 | G111: =+G110-G104 -> 174.4305 | H111: DCO - PMP | I111: (XII) | J111: 298 | K111: Q3 | L111: 306 | M111: Q3 | N111: 280 | O111: Q3
B112: Liquidez geral (LG) | D112: ---- | E112: =E16/E30 -> 2.285312 | F112: =F16/F30 -> 2.0440083 | G112: =G16/G30 -> 2.3018573 | H112: Ativo corrente / Passivo corrente | J112: 1.67 | K112: Q2 | L112: 1.84 | M112: Q2 | N112: 1.97 | O112: Q2
B113: Liquidez reduzida (LR) | D113: ---- | E113: =(E16-E8)/E30 -> 2.0070796 | F113: =(F16-F8)/F30 -> 1.8569461 | G113: =(G16-G8)/G30 -> 2.0788741 | H113: [Ativo corrente - (Inv.+ A. biológicos)] / Passivo corrente | J113: 1.22 | K113: Q2 | L113: 1.09 | M113: Q2 | N113: 1.22 | O113: Q2
B114: Liquidez imediata (LI) | D114: ---- | E114: =E15/E30 -> 0.2536627 | F114: =F15/F30 -> 0.32684211 | G114: =G15/G30 -> 0.15046777 | H114: MFL / Passivo corrente
B116: Notas: | I116: Notas:
...

Sheet Inf adicionais
A1: Informações adicionais
B3: Informações sobre o volume de negócios (VN)
C5: 2022 | D5: 2023 | E5: 2024
B6: Mercado interno | C6: 26155041 | D6: 25272760 | E6: 26887524
B7: Mercado externo | C7: 8259486 | D7: 10831183 | E7: 12652953
B8: Total VN | C8: =C6+C7 -> 34414527 | D8: =D6+D7 -> 36103943 | E8: =E6+E7 -> 39540477
B11: Informações sobre compras e FSE
C13: 2022 | D13: 2023 | E13: 2024
B14: Mercado interno
B15: Compras | C15: 5722519 | D15: 5843641 | E15: 6146049
B16: FSE | C16: =-('DR Contab'!D12) -> 10472728 | D16: =-('DR Contab'!E12) -> 10062717 | E16: =-('DR Contab'!F12) -> 13103785
B17: Mercado externo
B18: Compras | C18: 3815012 | D18: 3581586 | E18: 4450588
B19: FSE | C19: 0 | D19: 0 | E19: 0
B22: Taxas de IVA aplicadas às vendas, serviços prestados, compras e FSE
B23: Rubricas | C23: Anos
C24: 2022 | D24: 2023 | E24: 2024
B25: Volume de negócios (vendas e serviços prest.) | C25: 0.23 | D25: 0.23 | E25: 0.23
B26: Compras | C26: 0.23 | D26: 0.23 | E26: 0.23
B27: FSE (exceto água) | C27: 0.23 | D27: 0.23 | E27: 0.23
B28: FSE - água | C28: 0.06 | D28: 0.06 | E28: 0.06
